{"1": "\u201c", "2": "\u4eba", "3": "\u4eec", "4": "\u5e38", "5": "\u8bf4", "6": "\u751f", "7": "\u6d3b", "8": "\u662f", "9": "\u4e00", "10": "\u90e8", "11": "\u6559", "12": "\u79d1", "13": "\u4e66", "14": "\uff0c", "15": "\u800c", "16": "\u8840", "17": "\u4e0e", "18": "\u706b", "19": "\u7684", "20": "\u6218", "21": "\u4e89", "22": "\u66f4", "23": "\u4e0d", "24": "\u53ef", "25": "\u591a", "26": "\u5f97", "27": "\u5979", "28": "\u786e", "29": "\u5b9e", "30": "\u540d", "31": "\u526f", "32": "\u5176", "33": "\u2018", "34": "\u6211", "35": "\u5927", "36": "\u5b66", "37": "\u2019", "38": "\u3002", "39": "\u5fc3", "40": "\u9759", "41": "\u6e10", "42": "\u77e5", "43": "\u6625", "44": "\u4f3c", "45": "\u6d77", "46": "\u82b1", "47": "\u6df1", "48": "\u6bcf", "49": "\u89c9", "50": "\u5f71", "51": "\u9999", "52": "\u5403", "53": "\u5c4e", "54": "\u4e1c", "55": "\u897f", "56": "\u8fde", "57": "\u6346", "58": "\u9ea6", "59": "\u4e5f", "60": "\u94e1", "61": "\u52a8", "62": "\u5440", "63": "\uff1f", "64": "\u4ed6", "65": "\u4e25", "66": "\u683c", "67": "\u8981", "68": "\u6c42", "69": "\u81ea", "70": "\u5df1", "71": "\u4ece", "72": "\u4e2a", "73": "\u4e3e", "74": "\u51fa", "75": "\u8eab", "76": "\u8fdb", "77": "\u58eb", "78": "\u6210", "79": "\u4e3a", "80": "\u4f1f", "81": "\u6c11", "82": "\u4e3b", "83": "\u4e49", "84": "\u8005", "85": "\u4f4d", "86": "\u6770", "87": "\u515a", "88": "\u5916", "89": "\u5171", "90": "\u4ea7", "91": "\u732e", "92": "\u4e8e", "93": "\u5d07", "94": "\u9ad8", "95": "\u4e8b", "96": "\u4e1a", "97": "\u5f81", "98": "\u672a", "99": "\u7528", "100": "\u8015", "101": "\u5730", "102": "\u548c", "103": "\u6709", "104": "\u6536", "105": "\u76ca", "106": "\u571f", "107": "\u51c6", "108": "\u8352", "109": "\u829c", "110": "\u8fd9", "111": "\u9996", "112": "\u5148", "113": "\u65cf", "114": "\u95ee", "115": "\u9898", "116": "\u611f", "117": "\u60c5", "118": "\u6254", "119": "\u4e86", "120": "\u4e24", "121": "\u9897", "122": "\u624b", "123": "\u69b4", "124": "\u5f39", "125": "\u4e0b", "126": "\u5b50", "127": "\u6e9c", "128": "\u53bb", "129": "\u5e9f", "130": "\u9664", "131": "\u524d", "132": "\u5b58", "133": "\u5728", "134": "\u6240", "135": "\u5236", "136": "\u5173", "137": "\u7cfb", "138": "\u5e76", "139": "\u72ec", "140": "\u5177", "141": "\u7279", "142": "\u6848", "143": "\u59cb", "144": "\u81f3", "145": "\u4eca", "146": "\u90fd", "147": "\u6ca1", "148": "\u8ddf", "149": "\u6cd5", "150": "\u5b98", "151": "\u63a5", "152": "\u89e6", "153": "\u8fc7", "154": "\u539f", "155": "\u544a", "156": "\u3001", "157": "\u88ab", "158": "\u4f60", "159": "\u53ea", "160": "\u628a", "161": "\u505a", "162": "\u597d", "163": "\u4f19", "164": "\u624d", "165": "\u670d", "166": "\u90a3", "167": "\u9635", "168": "\u6761", "169": "\u4ef6", "170": "\u867d", "171": "\u8270", "172": "\u82e6", "173": "\u5bb6", "174": "\u70ed", "175": "\u7740", "176": "\u5462", "177": "\u4ec0", "178": "\u4e48", "179": "\u62a2", "180": "\u5e72", "181": "\u8c01", "182": "\u4f5c", "183": "\u8d21", "184": "\u54ce", "185": "\u600e", "186": "\u6765", "187": "\u8bc9", "188": "\u58f0", "189": "\u79cd", "190": "\u83dc", "191": "\u70e6", "192": "\u607c", "193": "\u7d2f", "194": "\u65f6", "195": "\u5019", "196": "\uff1b", "197": "\u53e6", "198": "\u68da", "199": "\u964d", "200": "\u4ef7", "201": "\u7530", "202": "\u660e", "203": "\u767d", "204": "\u8d26", "205": "\u6295", "206": "\u672c", "207": "\u8d5a", "208": "\u5229", "209": "\u6da6", "210": "\u8d77", "211": "\u7801", "212": "\u9053", "213": "\u7406", "214": "\u957f", "215": "\u5c81", "216": "\u6708", "217": "\u4f20", "218": "\u7edf", "219": "\u6fc0", "220": "\u536b", "221": "\u66fe", "222": "\u7ecf", "223": "\u5386", "224": "\u8f66", "225": "\u4e0a", "226": "\u8bdd", "227": "\u6562", "228": "\u8bb2", "229": "\u5230", "230": "\u5355", "231": "\u5c31", "232": "\u7136", "233": "\u8def", "234": "\u961f", "235": "\u4f0d", "236": "\u91cc", "237": "\u8083", "238": "\u65e0", "239": "\u4f46", "240": "\u5931", "241": "\u671b", "242": "\u8ba9", "243": "\u540c", "244": "\u8fce", "245": "\u827e", "246": "\u6ecb", "247": "\u75c5", "248": "\uff01", "249": "\u73b0", "250": "\u4ee3", "251": "\u5316", "252": "\u8230", "253": "\u6280", "254": "\u672f", "255": "\u7b80", "256": "\u5c97", "257": "\u5f53", "258": "\u5f88", "259": "\u4f24", "260": "\u8ba4", "261": "\u8f88", "262": "\u7b97", "263": "\u5b8c", "264": "\u5b69", "265": "\u5929", "266": "\u8d44", "267": "\u8fd8", "268": "\u9519", "269": "\u4e60", "270": "\u7ee9", "271": "\u822c", "272": "\u5c0f", "273": "\u8f83", "274": "\u8001", "275": "\u5e08", "276": "\u522b", "277": "\u559c", "278": "\u6b22", "279": "\u53cd", "280": "\u9ca8", "281": "\u9c7c", "282": "\u8f6f", "283": "\u9aa8", "284": "\u7d20", "285": "\u2014", "286": "\u7c7b", "287": "\u6297", "288": "\u764c", "289": "\u9632", "290": "\u6cbb", "291": "\u65b0", "292": "\u5e0c", "293": "\u80b2", "294": "\u9762", "295": "\u5411", "296": "\u4e16", "297": "\u754c", "298": "\u201d", "299": "\u952e", "300": "\u80fd", "301": "\u5076", "302": "\u5c14", "303": "\u4e61", "304": "\u62e5", "305": "\u60f3", "306": "\u770b", "307": "\u7acb", "308": "\u5373", "309": "\u4f1a", "310": "\u906d", "311": "\u95ea", "312": "\u5f00", "313": "\u5f80", "314": "\u6392", "315": "\u53c8", "316": "\u6025", "317": "\u8f93", "318": "\u5bc6", "319": "\u70b9", "320": "\u949e", "321": "\u7968", "322": "\u613f", "323": "\u65c1", "324": "\u89c1", "325": "\u76ee", "326": "\u56fd", "327": "\u6b8b", "328": "\u75be", "329": "\u5206", "330": "\u5e03", "331": "\u77f3", "332": "\u5c71", "333": "\u533a", "334": "\u6f20", "335": "\u9ec4", "336": "\u65b9", "337": "\u53d1", "338": "\u6bd4", "339": "\u6563", "340": "\u5976", "341": "\u60a8", "342": "\u642c", "343": "\u884c", "344": "\u4fbf", "345": "\u5417", "346": "\u6253", "347": "\u51fb", "348": "\u4e4b", "349": "\u540e", "350": "\u603b", "351": "\u4f53", "352": "\u67d0", "353": "\u7559", "354": "\u75d5", "355": "\u8ff9", "356": "\u8bca", "357": "\u6dcb", "358": "\u5df4", "359": "\u8089", "360": "\u7624", "361": "\u773c", "362": "\u9ed1", "363": "\u8d5b", "364": "\u89c2", "365": "\u4f17", "366": "\u52a9", "367": "\u5a01", "368": "\u7d27", "369": "\u5f20", "370": "\u6781", "371": "\u8111", "372": "\u4e71", "373": "\u6015", "374": "\u5bf9", "375": "\u5fc5", "376": "\u987b", "377": "\u727a", "378": "\u7272", "379": "\u5e73", "380": "\u8861", "381": "\u6700", "382": "\u8fd1", "383": "\u5382", "384": "\u5907", "385": "\u9a6c", "386": "\u9879", "387": "\u518d", "388": "\u5438", "389": "\u6279", "390": "\u804c", "391": "\u5de5", "392": "\u5c11", "393": "\u6837", "394": "\u54cd", "395": "\u79ef", "396": "\u6027", "397": "\u594b", "398": "\u53d6", "399": "\u91cd", "400": "\u56e0", "401": "\u6539", "402": "\u9769", "403": "\u5c55", "404": "\u7a33", "405": "\u5b9a", "406": "\u4e34", "407": "\u8feb", "408": "\u4efb", "409": "\u52a1", "410": "\u5bc2", "411": "\u5bde", "412": "\u5bd2", "413": "\u51b7", "414": "\u98ce", "415": "\u9669", "416": "\u4fdd", "417": "\u8bc1", "418": "\u8db3", "419": "\u7403", "420": "\u8fd0", "421": "\u7531", "422": "\u5bb0", "423": "\u5b83", "424": "\u5e94", "425": "\u8be5", "426": "\u5143", "427": "\u9645", "428": "\u91d1", "429": "\u878d", "430": "\u5e02", "431": "\u573a", "432": "\u4e91", "433": "\u53d8", "434": "\u5e7b", "435": "\u7ade", "436": "\u5f02", "437": "\u70c8", "438": "\u53eb", "439": "\u513f", "440": "\u4e13", "441": "\u95e8", "442": "\u683d", "443": "\u5374", "444": "\u62e9", "445": "\u6cb9", "446": "\u516c", "447": "\u53f8", "448": "\u6d88", "449": "\u8d39", "450": "\u76f8", "451": "\u4e92", "452": "\u534f", "453": "\u5546", "454": "\u671f", "455": "\u57fa", "456": "\u7840", "457": "\u5efa", "458": "\u529b", "459": "\u4ed8", "460": "\u4e9b", "461": "\u6000", "462": "\u7edd", "463": "\u5904", "464": "\u8d70", "465": "\u5bb9", "466": "\u6613", "467": "\u5c40", "468": "\u8bbe", "469": "\u6743", "470": "\u6293", "471": "\u641e", "472": "\u9760", "473": "\u5587", "474": "\u53ed", "475": "\u9752", "476": "\u5e74", "477": "\u653f", "478": "\u601d", "479": "\u5df2", "480": "\u7075", "481": "\u5272", "482": "\u6574", "483": "\u9009", "484": "\u78b0", "485": "\u51e0", "486": "\u56de", "487": "\u5706", "488": "\u7a7a", "489": "\u5149", "490": "\u5982", "491": "\u6c34", "492": "\u7247", "493": "\u6726", "494": "\u80e7", "495": "\u300a", "496": "\u89e3", "497": "\u653e", "498": "\u56e2", "499": "\u7ed3", "500": "\u81f4", "501": "\u300b", "502": "\u6587", "503": "\u4e2d", "504": "\u63d0", "505": "\u673a", "506": "\u6784", "507": "\u81c3", "508": "\u80bf", "509": "\u5c42", "510": "\u6b21", "511": "\u53e0", "512": "\u7eed", "513": "\u7e41", "514": "\u6742", "515": "\u6548", "516": "\u7387", "517": "\u4f4e", "518": "\u5b89", "519": "\u5168", "520": "\u79df", "521": "\u968f", "522": "\u505c", "523": "\uff08", "524": "\u5de6", "525": "\u98df", "526": "\u6307", "527": "\uff09", "528": "\u9f50", "529": "\u8bc4", "530": "\u7a0b", "531": "\u5ea6", "532": "\u8d28", "533": "\u6f84", "534": "\u6ce5", "535": "\u7b49", "536": "\u6b64", "537": "\u5f62", "538": "\u4f55", "539": "\u679c", "540": "\u6b3e", "541": "\u8bc6", "542": "\u771f", "543": "\u5973", "544": "\u7a7f", "545": "\u7f3a", "546": "\u7236", "547": "\u6bcd", "548": "\u5c06", "549": "\u7ed9", "550": "\u793c", "551": "\u7269", "552": "\u6362", "553": "\u9644", "554": "\u5f55", "555": "\u5fcd", "556": "\u4f4f", "557": "\u53e5", "558": "\u6e90", "559": "\u8fdc", "560": "\u6d41", "561": "\u535a", "562": "\u7cbe", "563": "\u7ee7", "564": "\u627f", "565": "\u5f18", "566": "\u626c", "567": "\u5bdf", "568": "\u6570", "569": "\u7814", "570": "\u7a76", "571": "\u5ffd", "572": "\u89c6", "573": "\u9886", "574": "\u5bfc", "575": "\u4e4f", "576": "\u719f", "577": "\u5f3a", "578": "\u5f31", "579": "\u6d4e", "580": "\u52b2", "581": "\u8d8a", "582": "\u51b3", "583": "\u52b3", "584": "\u91cf", "585": "\u96be", "586": "\u52c7", "587": "\u8bed", "588": "\u6500", "589": "\u5cf0", "590": "\u5389", "591": "\u4eb2", "592": "\u5145", "593": "\u6ee1", "594": "\u7231", "595": "\u5174", "596": "\u5934", "597": "\u8f6e", "598": "\u5f1f", "599": "\u6237", "600": "\u8bec", "601": "\u5949", "602": "\u4ee4", "603": "\u79c1", "604": "\u5c3d", "605": "\u77dc", "606": "\u60a3", "607": "\u907f", "608": "\u6b7b", "609": "\u8d24", "610": "\u5c45", "611": "\u53d7", "612": "\u7984", "613": "\u4ee5", "614": "\u4ea1", "615": "\u5c0a", "616": "\u663e", "617": "\u7ba1", "618": "\u61c2", "619": "\u827a", "620": "\u517b", "621": "\u4e30", "622": "\u5bcc", "623": "\u5ba1", "624": "\u7f8e", "625": "\u5404", "626": "\u503c", "627": "\u7eaa", "628": "\u5ff5", "629": "\u94b1", "630": "\u7248", "631": "\u4e45", "632": "\u670b", "633": "\u53cb", "634": "\u5b57", "635": "\u575a", "636": "\u4fe1", "637": "\u8f89", "638": "\u714c", "639": "\u6c7d", "640": "\u76f4", "641": "\u901a", "642": "\u653b", "643": "\u4ea4", "644": "\u60e6", "645": "\u811a", "646": "\u8fc8", "647": "\u558a", "648": "\u6551", "649": "\u547d", "650": "\u554a", "651": "\u8bae", "652": "\u6ce8", "653": "\u7956", "654": "\u9020", "655": "\u7eb8", "656": "\u7af9", "657": "\u5199", "658": "\u57ce", "659": "\u6cbf", "660": "\u6e56", "661": "\u7eff", "662": "\u5e26", "663": "\u886c", "664": "\u6258", "665": "\u6062", "666": "\u5b8f", "667": "\u7b51", "668": "\u8bd7", "669": "\u8df3", "670": "\u8dc3", "671": "\u97f3", "672": "\u4e50", "673": "\u7545", "674": "\u62a4", "675": "\u5305", "676": "\u6797", "677": "\u96c6", "678": "\u5408", "679": "\u4fb5", "680": "\u72af", "681": "\u4f9d", "682": "\u4eab", "683": "\u6728", "684": "\u8b66", "685": "\u53e3", "686": "\u9a7e", "687": "\u9a76", "688": "\u5458", "689": "\u533b", "690": "\u836f", "691": "\u8d23", "692": "\u79bb", "693": "\u88c5", "694": "\u610f", "695": "\u4ead", "696": "\u5356", "697": "\u70df", "698": "\u9152", "699": "\u54c1", "700": "\u7535", "701": "\u5e2e", "702": "\u9700", "703": "\u519b", "704": "\u67f1", "705": "\u767e", "706": "\u59d3", "707": "\u7a77", "708": "\u627e", "709": "\u793e", "710": "\u62d2", "711": "\u8854", "712": "\u5c5e", "713": "\u7ea7", "714": "\u53ca", "715": "\u95f4", "716": "\u79f0", "717": "\u547c", "718": "\u6216", "719": "\u52a0", "720": "\u5fd7", "721": "\u6b63", "722": "\u54e5", "723": "\u54c8", "724": "\u96cf", "725": "\u4f11", "726": "\u5439", "727": "\u5413", "728": "\u60e7", "729": "\u722a", "730": "\u7259", "731": "\u9976", "732": "\u864e", "733": "\u51a0", "734": "\u53e4", "735": "\u6234", "736": "\u4e4c", "737": "\u7eb1", "738": "\u60f9", "739": "\u6740", "740": "\u7978", "741": "\u5a46", "742": "\u5bfb", "743": "\u59d0", "744": "\u4f01", "745": "\u80a1", "746": "\u4efd", "747": "\u5360", "748": "\u63a7", "749": "\u5feb", "750": "\u9988", "751": "\u9274", "752": "\u7c73", "753": "\u65d7", "754": "\u76fc", "755": "\u6cae", "756": "\u4e27", "757": "\u8c0a", "758": "\u7ae0", "759": "\u8d27", "760": "\u4e70", "761": "\u7a0e", "762": "\u5b9c", "763": "\u5012", "764": "\u9709", "765": "\u8425", "766": "\u54d1", "767": "\u4e8f", "768": "\u724c", "769": "\u7701", "770": "\u65e5", "771": "\u6101", "772": "\u56f0", "773": "\u5e9c", "774": "\u8349", "775": "\u755c", "776": "\u8bd5", "777": "\u9a8c", "778": "\u6cbe", "779": "\u8df5", "780": "\u6cea", "781": "\u6cc9", "782": "\u6d8c", "783": "\u8bb8", "784": "\u8877", "785": "\u8c22", "786": "\u7238", "787": "\u8363", "788": "\u8a89", "789": "\u94c1", "790": "\u6b4c", "791": "\u5531", "792": "\uff1a", "793": "\u5371", "794": "\u8f7b", "795": "\u78e8", "796": "\u7ec3", "797": "\u82e5", "798": "\u59d4", "799": "\u5c48", "800": "\u8c08", "801": "\u8d2b", "802": "\u7ae5", "803": "\u8bfb", "804": "\u6b67", "805": "\u5b54", "806": "\u7aef", "807": "\u6311", "808": "\u5254", "809": "\u8ba5", "810": "\u8bbd", "811": "\u6b3a", "812": "\u538b", "813": "\u65bd", "814": "\u9001", "815": "\u6e29", "816": "\u6696", "817": "\u62ff", "818": "\u786c", "819": "\u63aa", "820": "\u6c14", "821": "\u529f", "822": "\u592b", "823": "\u5fe7", "824": "\u6b32", "825": "\u5883", "826": "\u6b65", "827": "\u666f", "828": "\u72c2", "829": "\u66b4", "830": "\u96e8", "831": "\u96f7", "832": "\u5288", "833": "\u5343", "834": "\u6068", "835": "\u5426", "836": "\u609f", "837": "\u636e", "838": "\u6b20", "839": "\u9014", "840": "\u5370", "841": "\u8c61", "842": "\u8bc8", "843": "\u9a97", "844": "\u5ba2", "845": "\u54e6", "846": "\u9000", "847": "\u7f18", "848": "\u561b", "849": "\u4e3d", "850": "\u542c", "851": "\u7ec8", "852": "\u5f52", "853": "\u52c9", "854": "\u652f", "855": "\u6491", "856": "\u620f", "857": "\u6f14", "858": "\u8179", "859": "\u6b49", "860": "\u5e55", "861": "\u9636", "862": "\u6821", "863": "\u529e", "864": "\u8910", "865": "\u5e90", "866": "\u803d", "867": "\u8bef", "868": "\u592a", "869": "\u775b", "870": "\u56ed", "871": "\u5f0f", "872": "\u578b", "873": "\u5a31", "874": "\u65c5", "875": "\u6e38", "876": "\u5047", "877": "\u6751", "878": "\u4f34", "879": "\u5219", "880": "\u6321", "881": "\u8bf1", "882": "\u60d1", "883": "\u975e", "884": "\u75db", "885": "\uff23", "886": "\uff34", "887": "\uff38", "888": "\u66f2", "889": "\u5267", "890": "\u57f9", "891": "\u826f", "892": "\u9047", "893": "\u6beb", "894": "\u72b9", "895": "\u8c6b", "896": "\u51b2", "897": "\u5584", "898": "\u4f7f", "899": "\u5e1d", "900": "\u62a5", "901": "\u6843", "902": "\u83ca", "903": "\u98d2", "904": "\u9662", "905": "\u854a", "906": "\u8776", "907": "\u7b54", "908": "\u54c4", "909": "\u5141", "910": "\u52aa", "911": "\u7ea2", "912": "\u638c", "913": "\u54df", "914": "\u7b14", "915": "\u950b", "916": "\u77e3", "917": "\u644a", "918": "\u8d62", "919": "\u623f", "920": "\u5c4b", "921": "\u5347", "922": "\u552e", "923": "\u72ee", "924": "\u8c79", "925": "\u7334", "926": "\u6001", "927": "\u73af", "928": "\u8c10", "929": "\u6cf3", "930": "\u6ee9", "931": "\u722c", "932": "\u5cad", "933": "\u5e95", "934": "\u654c", "935": "\u56f4", "936": "\u527f", "937": "\u65e7", "938": "\u53db", "939": "\u9003", "940": "\u5341", "941": "\u523b", "942": "\u8896", "943": "\u5377", "944": "\u62f3", "945": "\u5175", "946": "\u6bb5", "947": "\u5659", "948": "\u6d51", "949": "\u6d4a", "950": "\u73e0", "951": "\u5a03", "952": "\u5fd8", "953": "\u803b", "954": "\u8fb1", "955": "\u5468", "956": "\u8bb0", "957": "\u9547", "958": "\u4e01", "959": "\u501f", "960": "\u888b", "961": "\u8d22", "962": "\u817f", "963": "\u6413", "964": "\u7ef3", "965": "\u83b7", "966": "\u54b1", "967": "\u843d", "968": "\u5021", "969": "\u516b", "970": "\u4ed9", "971": "\u8a00", "972": "\u667a", "973": "\u6167", "974": "\u6676", "975": "\u51dd", "976": "\u7ebf", "977": "\u5185", "978": "\u6839", "979": "\u77db", "980": "\u76fe", "981": "\u5207", "982": "\u7fa4", "983": "\u76d1", "984": "\u7763", "985": "\u4fee", "986": "\u8ba2", "987": "\u8865", "988": "\u89c4", "989": "\u72ed", "990": "\u9698", "991": "\u6ede", "992": "\u6cdb", "993": "\u6263", "994": "\u6807", "995": "\u9776", "996": "\u54ea", "997": "\u50cf", "998": "\u7315", "999": "\u65ad", "1000": "\u5b9d", "1001": "\u6e7f", "1002": "\u7a74", "1003": "\u9648", "1004": "\u5217", "1005": "\u7533", "1006": "\u8bf7", "1007": "\u2026", "1008": "\u751a", "1009": "\u5ba3", "1010": "\u5427", "1011": "\u53ee", "1012": "\u5631", "1013": "\u8c41", "1014": "\u8ba1", "1015": "\u914d", "1016": "\u4eae", "1017": "\u707f", "1018": "\u70c2", "1019": "\u5fbd", "1020": "\u677f", "1021": "\u8272", "1022": "\u5473", "1023": "\u8033", "1024": "\u5988", "1025": "\u978b", "1026": "\u5565", "1027": "\u8131", "1028": "\u8857", "1029": "\u5f15", "1030": "\u6545", "1031": "\u6b23", "1032": "\u8d4f", "1033": "\u5ead", "1034": "\u5802", "1035": "\u8bfe", "1036": "\u64ad", "1037": "\u8f9b", "1038": "\u60ef", "1039": "\u95f2", "1040": "\u8212", "1041": "\u51ed", "1042": "\u4e14", "1043": "\u62db", "1044": "\u8fb9", "1045": "\u767b", "1046": "\u5e7f", "1047": "\u68f5", "1048": "\u6811", "1049": "\u540a", "1050": "\u9971", "1051": "\u8c03", "1052": "\u6599", "1053": "\u6869", "1054": "\u67f4", "1055": "\u7a81", "1056": "\u7adf", "1057": "\u94a2", "1058": "\u70bc", "1059": "\u6301", "1060": "\u8fd4", "1061": "\u6350", "1062": "\u5fae", "1063": "\u8584", "1064": "\u6d25", "1065": "\u8d34", "1066": "\u6170", "1067": "\u9f13", "1068": "\u52b1", "1069": "\u5eb7", "1070": "\u590d", "1071": "\u5475", "1072": "\u9f99", "1073": "\u821f", "1074": "\u7ec4", "1075": "\u7ec7", "1076": "\u60a6", "1077": "\u62b1", "1078": "\u6028", "1079": "\u8868", "1080": "\u5b59", "1081": "\u5065", "1082": "\u8c13", "1083": "\u8d35", "1084": "\u6212", "1085": "\u5947", "1086": "\u95fb", "1087": "\u54c9", "1088": "\u672b", "1089": "\u8bba", "1090": "\u9887", "1091": "\u5f03", "1092": "\u5e7d", "1093": "\u60dc", "1094": "\u7f6e", "1095": "\u514d", "1096": "\u85cf", "1097": "\u6e6e", "1098": "\u96f6", "1099": "\u6cef", "1100": "\u51b5", "1101": "\u4e4e", "1102": "\u82d4", "1103": "\u660f", "1104": "\u8680", "1105": "\u79bd", "1106": "\u9e1f", "1107": "\u5544", "1108": "\u6eaa", "1109": "\u79cb", "1110": "\u521a", "1111": "\u5144", "1112": "\u8bad", "1113": "\u65e2", "1114": "\u6b66", "1115": "\u53cc", "1116": "\u5446", "1117": "\u6309", "1118": "\u6269", "1119": "\u6a21", "1120": "\u5bb3", "1121": "\u5165", "1122": "\u80f8", "1123": "\u9614", "1124": "\u4ec5", "1125": "\u521b", "1126": "\u963f", "1127": "\u52bf", "1128": "\u53c2", "1129": "\u7537", "1130": "\u731b", "1131": "\u704c", "1132": "\u76b1", "1133": "\u7709", "1134": "\u56b7", "1135": "\u624e", "1136": "\u7ea6", "1137": "\u7ef4", "1138": "\u8d1f", "1139": "\u5b88", "1140": "\u517c", "1141": "\u7834", "1142": "\u88b1", "1143": "\u80cc", "1144": "\u9972", "1145": "\u7626", "1146": "\u4ecd", "1147": "\u9a8f", "1148": "\u9a70", "1149": "\u9a8b", "1150": "\u7586", "1151": "\u7cae", "1152": "\u6b86", "1153": "\u59bb", "1154": "\u54fc", "1155": "\u9f3b", "1156": "\u649e", "1157": "\u5357", "1158": "\u5899", "1159": "\u635f", "1160": "\u6241", "1161": "\u5e01", "1162": "\u4f9b", "1163": "\u73cd", "1164": "\u53bf", "1165": "\u6f5c", "1166": "\u5824", "1167": "\u63e1", "1168": "\u795e", "1169": "\u966a", "1170": "\u7262", "1171": "\u53f2", "1172": "\u4f10", "1173": "\u7267", "1174": "\u6446", "1175": "\u8f9e", "1176": "\u5a18", "1177": "\u7266", "1178": "\u725b", "1179": "\u8ffd", "1180": "\u8282", "1181": "\u591f", "1182": "\u9075", "1183": "\u4e07", "1184": "\u67e5", "1185": "\u7518", "1186": "\u534a", "1187": "\u6b8a", "1188": "\u656c", "1189": "\u8eaf", "1190": "\u606f", "1191": "\u9ece", "1192": "\u77ed", "1193": "\u6682", "1194": "\u9650", "1195": "\u8d85", "1196": "\u4f18", "1197": "\u79c0", "1198": "\u514b", "1199": "\u51e1", "1200": "\u6302", "1201": "\u9a7b", "1202": "\u91c7", "1203": "\u507f", "1204": "\u8d38", "1205": "\u8f6c", "1206": "\u519c", "1207": "\u6f02", "1208": "\u5ec9", "1209": "\u6d01", "1210": "\u5f8b", "1211": "\u5634", "1212": "\u5c82", "1213": "\u8d37", "1214": "\u5317", "1215": "\u91ce", "1216": "\u8be6", "1217": "\u7ec6", "1218": "\u94fa", "1219": "\u8f68", "1220": "\u68b0", "1221": "\u65fa", "1222": "\u76db", "1223": "\u68c9", "1224": "\u5212", "1225": "\u566a", "1226": "\u7eba", "1227": "\u666e", "1228": "\u904d", "1229": "\u5dee", "1230": "\u56fe", "1231": "\u865a", "1232": "\u8822", "1233": "\u65e9", "1234": "\u96c4", "1235": "\u58ee", "1236": "\u575d", "1237": "\u7d0a", "1238": "\u7981", "1239": "\u8d5e", "1240": "\u53f9", "1241": "\u9ed8", "1242": "\u6597", "1243": "\u60ca", "1244": "\u4e09", "1245": "\u7b79", "1246": "\u5b85", "1247": "\u4f8b", "1248": "\u7b56", "1249": "\u8ba8", "1250": "\u73ed", "1251": "\u969c", "1252": "\u949f", "1253": "\u8da3", "1254": "\u7b2c", "1255": "\u4e8c", "1256": "\u52e4", "1257": "\u707c", "1258": "\u7bc7", "1259": "\u70ac", "1260": "\u6c38", "1261": "\u8bc0", "1262": "\u7bb1", "1263": "\u7b11", "1264": "\u4f6f", "1265": "\u731c", "1266": "\u9f84", "1267": "\u8138", "1268": "\u6298", "1269": "\u8936", "1270": "\u987f", "1271": "\u5b81", "1272": "\u9b42", "1273": "\u67d4", "1274": "\u91ca", "1275": "\u62cd", "1276": "\u7167", "1277": "\u8d56", "1278": "\u8bbf", "1279": "\u900f", "1280": "\u5a92", "1281": "\u589e", "1282": "\u51cf", "1283": "\u51fd", "1284": "\u5747", "1285": "\u4f2a", "1286": "\u6df7", "1287": "\u89d2", "1288": "\u539a", "1289": "\u542f", "1290": "\u9002", "1291": "\u63cf", "1292": "\u8ff0", "1293": "\u7c89", "1294": "\u788e", "1295": "\u5f77", "1296": "\u5fa8", "1297": "\u96c0", "1298": "\u6e05", "1299": "\u695a", "1300": "\u6324", "1301": "\u5723", "1302": "\u6328", "1303": "\u5e84", "1304": "\u7a3c", "1305": "\u5bbd", "1306": "\u5fe1", "1307": "\u518c", "1308": "\u684c", "1309": "\u7f20", "1310": "\u632b", "1311": "\u5e78", "1312": "\u723d", "1313": "\u6717", "1314": "\u4e08", "1315": "\u60b2", "1316": "\u59b9", "1317": "\u7898", "1318": "\uff21", "1319": "\uff24", "1320": "\u72b6", "1321": "\u6790", "1322": "\u8bf8", "1323": "\u8f9f", "1324": "\u592e", "1325": "\u63a8", "1326": "\u8d8b", "1327": "\u8d3a", "1328": "\u8fc1", "1329": "\u63e9", "1330": "\u9a82", "1331": "\u5566", "1332": "\u9489", "1333": "\u6b47", "1334": "\u62bd", "1335": "\u515c", "1336": "\u638f", "1337": "\u76d2", "1338": "\u53fc", "1339": "\u7237", "1340": "\u5fd2", "1341": "\u62ac", "1342": "\u62c9", "1343": "\u53f3", "1344": "\u76ae", "1345": "\u706f", "1346": "\u5239", "1347": "\u86c7", "1348": "\u5c3e", "1349": "\u902e", "1350": "\u987e", "1351": "\u8bfa", "1352": "\u8bcd", "1353": "\u6089", "1354": "\u53f7", "1355": "\u8e0f", "1356": "\u552f", "1357": "\u997f", "1358": "\u6e34", "1359": "\u67b6", "1360": "\u6865", "1361": "\u6881", "1362": "\u8054", "1363": "\u8106", "1364": "\u54ed", "1365": "\u6094", "1366": "\u633a", "1367": "\u602a", "1368": "\u756a", "1369": "\u6325", "1370": "\u5750", "1371": "\u8d2d", "1372": "\u75bc", "1373": "\u5f84", "1374": "\u8d2f", "1375": "\u5f7b", "1376": "\u7eb2", "1377": "\u5450", "1378": "\u5806", "1379": "\u81c2", "1380": "\u5ea7", "1381": "\u5761", "1382": "\u5662", "1383": "\u675f", "1384": "\u574f", "1385": "\u59e8", "1386": "\u96ea", "1387": "\u51bb", "1388": "\u9505", "1389": "\u7089", "1390": "\u697c", "1391": "\u8dd1", "1392": "\u6d3e", "1393": "\u65a9", "1394": "\u95f9", "1395": "\u51f6", "1396": "\u6284", "1397": "\u63ea", "1398": "\u5339", "1399": "\u6267", "1400": "\u6735", "1401": "\u8fbe", "1402": "\u500d", "1403": "\u8de8", "1404": "\u6127", "1405": "\u708e", "1406": "\u6d0b", "1407": "\u6ea2", "1408": "\u754f", "1409": "\u6b62", "1410": "\u5224", "1411": "\u7f34", "1412": "\u7eb3", "1413": "\u5e93", "1414": "\u80af", "1415": "\u6316", "1416": "\u6398", "1417": "\u5c24", "1418": "\u9981", "1419": "\u7f29", "1420": "\u574e", "1421": "\u5777", "1422": "\u996d", "1423": "\u821e", "1424": "\u810a", "1425": "\u548b", "1426": "\u8ddd", "1427": "\u7efc", "1428": "\u8499", "1429": "\u7f9e", "1430": "\u6233", "1431": "\u5e3d", "1432": "\u6c89", "1433": "\u7b5d", "1434": "\u80c6", "1435": "\u62d4", "1436": "\u7ecc", "1437": "\u62fc", "1438": "\u640f", "1439": "\u6602", "1440": "\u7565", "1441": "\u95f7", "1442": "\u7126", "1443": "\u5b64", "1444": "\u8239", "1445": "\u6447", "1446": "\u8017", "1447": "\u6e3a", "1448": "\u832b", "1449": "\u4f59", "1450": "\u953b", "1451": "\u8c1a", "1452": "\u66f0", "1453": "\u626e", "1454": "\u8336", "1455": "\u6ce1", "1456": "\u5ba4", "1457": "\u5854", "1458": "\u5c16", "1459": "\u987a", "1460": "\u8e29", "1461": "\u9633", "1462": "\u8003", "1463": "\u8651", "1464": "\u6d4b", "1465": "\u94f6", "1466": "\u5957", "1467": "\u8303", "1468": "\u955c", "1469": "\u8c26", "1470": "\u4e43", "1471": "\u8c6a", "1472": "\u62c5", "1473": "\u5639", "1474": "\u8c0b", "1475": "\u7ad9", "1476": "\u68af", "1477": "\u5237", "1478": "\u6f06", "1479": "\u6d1e", "1480": "\u4fc3", "1481": "\u8010", "1482": "\u82db", "1483": "\u9510", "1484": "\u77e9", "1485": "\u5984", "1486": "\u83f2", "1487": "\u671d", "1488": "\u9884", "1489": "\u8ff7", "1490": "\u4ec7", "1491": "\u9010", "1492": "\u6dd8", "1493": "\u6c70", "1494": "\u5ef6", "1495": "\u7597", "1496": "\u5b55", "1497": "\u54fa", "1498": "\u4e73", "1499": "\u7ed5", "1500": "\u5192", "1501": "\u88c1", "1502": "\u90d1", "1503": "\u5401", "1504": "\u80de", "1505": "\u52ff", "1506": "\u6050", "1507": "\u80c1", "1508": "\u529d", "1509": "\u8116", "1510": "\u6897", "1511": "\u632f", "1512": "\u8d29", "1513": "\u7897", "1514": "\u7a0d", "1515": "\u9877", "1516": "\u5c01", "1517": "\u7687", "1518": "\u8d25", "1519": "\u8eb2", "1520": "\u6c99", "1521": "\u7a97", "1522": "\u89c8", "1523": "\u9707", "1524": "\u521d", "1525": "\u793a", "1526": "\u6c13", "1527": "\u53f0", "1528": "\u7f6a", "1529": "\u5200", "1530": "\u903c", "1531": "\u6b79", "1532": "\u5f92", "1533": "\u543c", "1534": "\u8457", "1535": "\u76d0", "1536": "\u8393", "1537": "\u62c6", "1538": "\u4fa8", "1539": "\u7737", "1540": "\u4e88", "1541": "\u5f04", "1542": "\u4ef0", "1543": "\u95ef", "1544": "\u8d76", "1545": "\u6389", "1546": "\u5238", "1547": "\u8be3", "1548": "\u73a9", "1549": "\u7656", "1550": "\u94bb", "1551": "\u6479", "1552": "\u4eff", "1553": "\u7b4b", "1554": "\u753b", "1555": "\u56fa", "1556": "\u6670", "1557": "\u6367", "1558": "\u76c8", "1559": "\u5766", "1560": "\u7f1d", "1561": "\u8154", "1562": "\u5de1", "1563": "\u5668", "1564": "\u57ab", "1565": "\u9488", "1566": "\u6838", "1567": "\u7b26", "1568": "\u4fe9", "1569": "\u8c28", "1570": "\u806a", "1571": "\u5178", "1572": "\u96c5", "1573": "\u5956", "1574": "\u9910", "1575": "\u5bb4", "1576": "\u5385", "1577": "\u5bbe", "1578": "\u6643", "1579": "\u7eea", "1580": "\u4f73", "1581": "\u5510", "1582": "\u5b8b", "1583": "\u810d", "1584": "\u7099", "1585": "\u82b3", "1586": "\u542b", "1587": "\u5f85", "1588": "\u6750", "1589": "\u6620", "1590": "\u62d6", "1591": "\u5915", "1592": "\u57df", "1593": "\u5de8", "1594": "\u65e6", "1595": "\u71ac", "1596": "\u5250", "1597": "\u6c5f", "1598": "\u7cdf", "1599": "\u7cd5", "1600": "\u79d8", "1601": "\u65a1", "1602": "\u65cb", "1603": "\u6bd5", "1604": "\u5f70", "1605": "\u51d1", "1606": "\u63f4", "1607": "\u98de", "1608": "\u7761", "1609": "\u5ce1", "1610": "\u8c37", "1611": "\u8fdd", "1612": "\u82f1", "1613": "\u804a", "1614": "\u54ac", "1615": "\u68cb", "1616": "\u76d8", "1617": "\u7686", "1618": "\u80a9", "1619": "\u68d2", "1620": "\u6cb3", "1621": "\u5954", "1622": "\u6d6a", "1623": "\u9006", "1624": "\u8bf5", "1625": "\u80dc", "1626": "\u6bb7", "1627": "\u6734", "1628": "\u534e", "1629": "\u5a5a", "1630": "\u559d", "1631": "\u6401", "1632": "\u5bbf", "1633": "\u820d", "1634": "\u6512", "1635": "\u6691", "1636": "\u9a84", "1637": "\u50b2", "1638": "\u6168", "1639": "\u8d2a", "1640": "\u6c61", "1641": "\u8d3f", "1642": "\u5f87", "1643": "\u5f0a", "1644": "\u6789", "1645": "\u5211", "1646": "\u88a2", "1647": "\u51c9", "1648": "\u51a4", "1649": "\u677e", "1650": "\u66ff", "1651": "\u626b", "1652": "\u5893", "1653": "\u5e8f", "1654": "\u8fa9", "1655": "\u5757", "1656": "\u5e97", "1657": "\u9605", "1658": "\u5509", "1659": "\u4e95", "1660": "\u7434", "1661": "\u62bc", "1662": "\u59c6", "1663": "\u8d9f", "1664": "\u7fd8", "1665": "\u5112", "1666": "\u9038", "1667": "\u6e17", "1668": "\u900d", "1669": "\u9065", "1670": "\u661f", "1671": "\u611a", "1672": "\u665a", "1673": "\u9501", "1674": "\u82cd", "1675": "\u7f8a", "1676": "\u5938", "1677": "\u989c", "1678": "\u4e7e", "1679": "\u5764", "1680": "\u7a91", "1681": "\u504c", "1682": "\u62b5", "1683": "\u5f26", "1684": "\u6452", "1685": "\u77a7", "1686": "\u4f30", "1687": "\u7f16", "1688": "\u5999", "1689": "\u63d2", "1690": "\u8be8", "1691": "\u6296", "1692": "\u5eb8", "1693": "\u4fd7", "1694": "\u64e6", "1695": "\u51c0", "1696": "\u6444", "1697": "\u5948", "1698": "\u6323", "1699": "\u96d5", "1700": "\u5851", "1701": "\u9057", "1702": "\u5740", "1703": "\u7f00", "1704": "\u6db5", "1705": "\u96c1", "1706": "\u816e", "1707": "\u83cc", "1708": "\u5448", "1709": "\u4f69", "1710": "\u5c1d", "1711": "\u751c", "1712": "\u61c8", "1713": "\u963b", "1714": "\u6c72", "1715": "\u5490", "1716": "\u5b63", "1717": "\u4ffa", "1718": "\u6458", "1719": "\u680f", "1720": "\u95ed", "1721": "\u585e", "1722": "\u6db8", "1723": "\u5e8a", "1724": "\u5cb8", "1725": "\u733f", "1726": "\u557c", "1727": "\u63b0", "1728": "\u690d", "1729": "\u5e45", "1730": "\u7a8d", "1731": "\u9192", "1732": "\u4f3a", "1733": "\u65ed", "1734": "\u76ef", "1735": "\u73b7", "1736": "\u51b0", "1737": "\u51c4", "1738": "\uff0f", "1739": "\u6108", "1740": "\u7cca", "1741": "\u59e3", "1742": "\u598d", "1743": "\u8be2", "1744": "\u606a", "1745": "\u57ae", "1746": "\u8d31", "1747": "\u5361", "1748": "\u901f", "1749": "\u9896", "1750": "\u6fd2", "1751": "\u55d4", "1752": "\u54e8", "1753": "\u7891", "1754": "\u5bff", "1755": "\u664b", "1756": "\u6320", "1757": "\u6bc5", "1758": "\u5c1a", "1759": "\u90c1", "1760": "\u9a6d", "1761": "\u77ff", "1762": "\u4f38", "1763": "\u813e", "1764": "\u8dea", "1765": "\u978d", "1766": "\u5974", "1767": "\u4f25", "1768": "\u8fa3", "1769": "\u6349", "1770": "\u716e", "1771": "\u70b8", "1772": "\u70f9", "1773": "\u714e", "1774": "\u871c", "1775": "\u7cd6", "1776": "\u5d29", "1777": "\u4e22", "1778": "\u76d4", "1779": "\u7532", "1780": "\u7a00", "1781": "\u7f55", "1782": "\u54a7", "1783": "\u8bda", "1784": "\u51ac", "1785": "\u9012", "1786": "\u6441", "1787": "\uff22", "1788": "\uff30", "1789": "\u94ae", "1790": "\u6674", "1791": "\u59a5", "1792": "\u5faa", "1793": "\u50ac", "1794": "\u5242", "1795": "\u5269", "1796": "\u7206", "1797": "\u504f", "1798": "\u5085", "1799": "\u561f", "1800": "\u56d4", "1801": "\u80ce", "1802": "\u6bdb", "1803": "\u5077", "1804": "\u70ad", "1805": "\u6a61", "1806": "\u80f6", "1807": "\u614e", "1808": "\u9e23", "1809": "\u6c1b", "1810": "\u7194", "1811": "\u94f8", "1812": "\u52c3", "1813": "\u59ff", "1814": "\u5965", "1815": "\u5b70", "1816": "\u7ea0", "1817": "\u845b", "1818": "\u6377", "1819": "\u9550", "1820": "\u67aa", "1821": "\u9690", "1822": "\u6666", "1823": "\u8180", "1824": "\u8f9c", "1825": "\u6de1", "1826": "\u8f86", "1827": "\u8f7f", "1828": "\u5f7c", "1829": "\u8377", "1830": "\u59d1", "1831": "\u5fc6", "1832": "\u631a", "1833": "\u593a", "1834": "\u6dfb", "1835": "\u4e32", "1836": "\u5520", "1837": "\u55d1", "1838": "\u614c", "1839": "\u6d82", "1840": "\u5600", "1841": "\u5495", "1842": "\u8902", "1843": "\u8e72", "1844": "\u4ec6", "1845": "\u8461", "1846": "\u8404", "1847": "\u5987", "1848": "\u8463", "1849": "\u62d0", "1850": "\u541b", "1851": "\u8361", "1852": "\u9f87", "1853": "\u5f69", "1854": "\u54b8", "1855": "\u4e1d", "1856": "\u61be", "1857": "\u60e0", "1858": "\u6e21", "1859": "\u6c49", "1860": "\u5348", "1861": "\u75af", "1862": "\u4fed", "1863": "\u805a", "1864": "\u53c9", "1865": "\u6863", "1866": "\u7a84", "1867": "\u8058", "1868": "\u5782", "1869": "\u6d6e", "1870": "\u80a5", "1871": "\u7caa", "1872": "\u810f", "1873": "\u6355", "1874": "\u90ce", "1875": "\u54c0", "1876": "\u9c9c", "1877": "\u5e1c", "1878": "\u706d", "1879": "\u6c64", "1880": "\u55ec", "1881": "\u83ab", "1882": "\u4e59", "1883": "\u9022", "1884": "\u582a", "1885": "\u987d", "1886": "\u524a", "1887": "\u63a9", "1888": "\u8bde", "1889": "\u798f", "1890": "\u5218", "1891": "\u6d2a", "1892": "\u4e94", "1893": "\u4ecb", "1894": "\u7ecd", "1895": "\u90af", "1896": "\u56db", "1897": "\u6d66", "1898": "\u664f", "1899": "\u4eac", "1900": "\u90f8", "1901": "\u4e5d", "1902": "\u6caa", "1903": "\u6c9f", "1904": "\u622a", "1905": "\u4e03", "1906": "\u4ebf", "1907": "\u65a4", "1908": "\u989d", "1909": "\u590f", "1910": "\u655e", "1911": "\u6f6e", "1912": "\uff12", "1913": "\uff13", "1914": "\u5434", "1915": "\u6cfe", "1916": "\u4e9a", "1917": "\u6e7e", "1918": "\uff16", "1919": "\uff10", "1920": "\u7f51", "1921": "\uff15", "1922": "\uff18", "1923": "\uff0e", "1924": "\u74e6", "1925": "\uff14", "1926": "\uff17", "1927": "\uff05", "1928": "\uff11", "1929": "\uff19", "1930": "\u5fe0", "1931": "\u81e3", "1932": "\u9063", "1933": "\u68c0", "1934": "\u516d", "1935": "\u300e", "1936": "\u300f", "1937": "\u53ec", "1938": "\u8f67", "1939": "\uff28", "1940": "\u5428", "1941": "\u738b", "1942": "\u822a", "1943": "\u54a8", "1944": "\u9891", "1945": "\u62e8", "1946": "\u6eda", "1947": "\u9694", "1948": "\u82ef", "1949": "\u70ef", "1950": "\u6e2f", "1951": "\u8102", "1952": "\u52d8", "1953": "\u63a2", "1954": "\u76c6", "1955": "\u7164", "1956": "\u50a8", "1957": "\u00b7", "1958": "\u9e93", "1959": "\u7554", "1960": "\u8c8c", "1961": "\u8d75", "1962": "\u8000", "1963": "\u5733", "1964": "\u7738", "1965": "\u8258", "1966": "\u6c5b", "1967": "\u8247", "1968": "\u8baf", "1969": "\u8fc5", "1970": "\u8d74", "1971": "\u6e58", "1972": "\u82b7", "1973": "\u4f97", "1974": "\u76f2", "1975": "\u9093", "1976": "\u5170", "1977": "\u82d7", "1978": "\u674e", "1979": "\u5e86", "1980": "\u710a", "1981": "\u9655", "1982": "\u6e20", "1983": "\u5f79", "1984": "\u9500", "1985": "\u67cf", "1986": "\u5dde", "1987": "\u682a", "1988": "\u6d32", "1989": "\u6606", "1990": "\u67a2", "1991": "\u7ebd", "1992": "\u8fbd", "1993": "\u7b7e", "1994": "\u7f72", "1995": "\u62ec", "1996": "\u9986", "1997": "\u6b27", "1998": "\u6fb3", "1999": "\u76df", "2000": "\u541f", "2001": "\u71d5", "2002": "\uff0d", "2003": "\u795d", "2004": "\u6cfd", "2005": "\u5e2d", "2006": "\u8036", "2007": "\u9686", "2008": "\u4eea", "2009": "\u6f29", "2010": "\u6da1", "2011": "\u9876", "2012": "\u633d", "2013": "\u9a91", "2014": "\u592f", "2015": "\u7a9c", "2016": "\u6bc1", "2017": "\u83b1", "2018": "\u5de2", "2019": "\u574a", "2020": "\u62ef", "2021": "\u901d", "2022": "\u77bb", "2023": "\u72fc", "2024": "\u7275", "2025": "\u9b44", "2026": "\u8f7d", "2027": "\u7965", "2028": "\u7bad", "2029": "\u58c1", "2030": "\u65f1", "2031": "\u9b54", "2032": "\u8086", "2033": "\u8650", "2034": "\u79be", "2035": "\u67af", "2036": "\u6d3c", "2037": "\u579b", "2038": "\u6ea5", "2039": "\u7ed1", "2040": "\u64cd", "2041": "\u523a", "2042": "\u54bd", "2043": "\u5589", "2044": "\u60ac", "2045": "\u6697", "2046": "\u7525", "2047": "\u4f8d", "2048": "\u800d", "2049": "\u69d0", "2050": "\u5367", "2051": "\u5708", "2052": "\u6746", "2053": "\u75ae", "2054": "\u7c97", "2055": "\u7cd9", "2056": "\u66f3", "2057": "\u5d2d", "2058": "\u53f6", "2059": "\u66ae", "2060": "\u558b", "2061": "\u6b89", "2062": "\u6cf0", "2063": "\u6251", "2064": "\u64a4", "2065": "\u6d1b", "2066": "\u829d", "2067": "\u57a3", "2068": "\u58a8", "2069": "\u8d4b", "2070": "\u7ffb", "2071": "\u8986", "2072": "\uff2f", "2073": "\uff2b", "2074": "\u835f", "2075": "\u8403", "2076": "\u8c2d", "2077": "\u946b", "2078": "\u53d4", "2079": "\u5ca9", "2080": "\u6885", "2081": "\u8862", "2082": "\u5055", "2083": "\u8e48", "2084": "\u5bab", "2085": "\u9b4f", "2086": "\u9619", "2087": "\u5b97", "2088": "\u5b9b", "2089": "\u68a6", "2090": "\u4fa7", "2091": "\u847a", "2092": "\u7115", "2093": "\u81fb", "2094": "\u90ca", "2095": "\u8398", "2096": "\u73b2", "2097": "\u73d1", "2098": "\u618b", "2099": "\u57cb", "2100": "\u832c", "2101": "\u55d3", "2102": "\u654f", "2103": "\u9646", "2104": "\u763e", "2105": "\u594f", "2106": "\u6388", "2107": "\u70e7", "2108": "\u6d3d", "2109": "\u6ee8", "2110": "\u8317", "2111": "\u7838", "2112": "\u79e9", "2113": "\u6768", "2114": "\u4f5b", "2115": "\u7c92", "2116": "\u6070", "2117": "\u6e85", "2118": "\u7b52", "2119": "\u6bef", "2120": "\u71c3", "2121": "\u9b13", "2122": "\u6591", "2123": "\u5a49", "2124": "\u9163", "2125": "\u97f5", "2126": "\u8302", "2127": "\u4e11", "2128": "\u4ff1", "2129": "\u7eb7", "2130": "\u8fea", "2131": "\u65af", "2132": "\u54ab", "2133": "\u5c3a", "2134": "\u66f9", "2135": "\u5018", "2136": "\u61e6", "2137": "\u82cf", "2138": "\u6478", "2139": "\u8150", "2140": "\u60e9", "2141": "\u5fb7", "2142": "\u4f50", "2143": "\u8d42", "2144": "\u5fcc", "2145": "\u618e", "2146": "\u9042", "2147": "\u8513", "2148": "\u9f20", "2149": "\u631f", "2150": "\u732b", "2151": "\u540f", "2152": "\u88c2", "2153": "\u8d43", "2154": "\u5be1", "2155": "\u6148", "2156": "\u9e21", "2157": "\u5106", "2158": "\u9774", "2159": "\u75d2", "2160": "\u834f", "2161": "\u80e5", "2162": "\u8839", "2163": "\u8f84", "2164": "\u9732", "2165": "\u7a83", "2166": "\u9a87", "2167": "\u675c", "2168": "\u64b0", "2169": "\u6555", "2170": "\u4ea6", "2171": "\u892a", "2172": "\u84ec", "2173": "\u6d53", "2174": "\u5dcd", "2175": "\u5cfb", "2176": "\u9177", "2177": "\u5e05", "2178": "\u5c4a", "2179": "\u8305", "2180": "\u8bd1", "2181": "\u98d8", "2182": "\u51e4", "2183": "\u51f0", "2184": "\u62d3", "2185": "\u9080", "2186": "\u5378", "2187": "\u591c", "2188": "\u5f98", "2189": "\u5f8a", "2190": "\u89c5", "2191": "\u8f70", "2192": "\u4e38", "2193": "\u503e", "2194": "\u6cfb", "2195": "\u7779", "2196": "\u8165", "2197": "\u4fd8", "2198": "\u864f", "2199": "\u5e87", "2200": "\u641c", "2201": "\u5180", "2202": "\u54d2", "2203": "\u7070", "2204": "\u6d12", "2205": "\u6668", "2206": "\u66e6", "2207": "\u62dc", "2208": "\u8d73", "2209": "\u9e2d", "2210": "\u6d74", "2211": "\u51ef", "2212": "\u80a0", "2213": "\u9050", "2214": "\u70ae", "2215": "\u785d", "2216": "\u8109", "2217": "\u64bc", "2218": "\u6b7c", "2219": "\u6e5b", "2220": "\u84dd", "2221": "\u5c04", "2222": "\u9524", "2223": "\u9e70", "2224": "\u7d22", "2225": "\u745a", "2226": "\u76d6", "2227": "\u55b7", "2228": "\u817e", "2229": "\u56ca", "2230": "\u960e", "2231": "\uff26", "2232": "\u6c47", "2233": "\u6ef4", "2234": "\u4e39", "2235": "\u676f", "2236": "\u74f6", "2237": "\u4ec1", "2238": "\u6c27", "2239": "\u75c7", "2240": "\u56bc", "2241": "\u820c", "2242": "\u5409", "2243": "\u58e4", "2244": "\u80e1", "2245": "\u634e", "2246": "\u8863", "2247": "\u9178", "2248": "\u61d2", "2249": "\u5de7", "2250": "\u739b", "2251": "\u7459", "2252": "\u5410", "2253": "\u6db2", "2254": "\u8c31", "2255": "\u7591", "2256": "\u5a07", "2257": "\u4fde", "2258": "\u7c98", "2259": "\u679d", "2260": "\u626d", "2261": "\u634f", "2262": "\u6f0f", "2263": "\u73bb", "2264": "\u7483", "2265": "\u64ae", "2266": "\u6eb6", "2267": "\u5960", "2268": "\u7682", "2269": "\u7519", "2270": "\u916e", "2271": "\u6bd2", "2272": "\u818f", "2273": "\u52a3", "2274": "\u508d", "2275": "\u6162", "2276": "\u7ede", "2277": "\u7750", "2278": "\u520a", "2279": "\u2161", "2280": "\u2162", "2281": "\u53e9", "2282": "\u62ab", "2283": "\u707e", "2284": "\u79e6", "2285": "\u6d59", "2286": "\u90ae", "2287": "\u5bf8", "2288": "\u7edc", "2289": "\u6c83", "2290": "\u625b", "2291": "\u7281", "2292": "\u6ce2", "2293": "\u852c", "2294": "\u5c51", "2295": "\u73ca", "2296": "\u7901", "2297": "\u68f1", "2298": "\u75a4", "2299": "\u9171", "2300": "\u7092", "2301": "\u6da8", "2302": "\u5c9b", "2303": "\u6f6d", "2304": "\u5c7f", "2305": "\u743c", "2306": "\u6d47", "2307": "\u8fb0", "2308": "\u6d69", "2309": "\u701a", "2310": "\u6c57", "2311": "\u903b", "2312": "\u752b", "2313": "\u620d", "2314": "\u780d", "2315": "\u6d17", "2316": "\u6fa1", "2317": "\u997a", "2318": "\u5f90", "2319": "\u6f2b", "2320": "\u9169", "2321": "\u914a", "2322": "\u9189", "2323": "\u67ec", "2324": "\u6ed4", "2325": "\u6c0f", "2326": "\u9a71", "2327": "\u67d3", "2328": "\u6982", "2329": "\u7f57", "2330": "\u5835", "2331": "\u6d89", "2332": "\u68ee", "2333": "\u4fc4", "2334": "\u4f0f", "2335": "\u4f0a", "2336": "\u5c61", "2337": "\u6270", "2338": "\u9b41", "2339": "\u836b", "2340": "\u5751", "2341": "\u7529", "2342": "\u9526", "2343": "\u6687", "2344": "\u8d64", "2345": "\u604b", "2346": "\u6a2a", "2347": "\u8679", "2348": "\u7a3f", "2349": "\u8bb4", "2350": "\u25b3", "2351": "\u4ef2", "2352": "\u6c60", "2353": "\u6a44", "2354": "\u6984", "2355": "\u4e1b", "2356": "\u5fd9", "2357": "\u788c", "2358": "\u6e14", "2359": "\u951a", "2360": "\u6628", "2361": "\u7eac", "2362": "\u4fa3", "2363": "\u51f3", "2364": "\u53ae", "2365": "\u6fef", "2366": "\u60a0", "2367": "\u75f4", "2368": "\u6f9c", "2369": "\u606c", "2370": "\u6f09", "2371": "\u62e6", "2372": "\u6ee4", "2373": "\u60ec", "2374": "\u6b96", "2375": "\u84c4", "2376": "\u5b09", "2377": "\u6d9b", "2378": "\u851a", "2379": "\u4f2f", "2380": "\u6c79", "2381": "\u63a0", "2382": "\u6012", "2383": "\u9532", "2384": "\u6380", "2385": "\u86d9", "2386": "\u74dc", "2387": "\u85e4", "2388": "\u642d", "2389": "\u8f98", "2390": "\u8f73", "2391": "\u7566", "2392": "\u526a", "2393": "\u4e54", "2394": "\u58d5", "2395": "\u5353", "2396": "\u5c3c", "2397": "\u7c4d", "2398": "\u85af", "2399": "\u6064", "2400": "\u4ed4", "2401": "\u88e4", "2402": "\u80a4", "2403": "\u68d5", "2404": "\u971c", "2405": "\u608d", "2406": "\u72e0", "2407": "\uff49", "2408": "\uff45", "2409": "\uff2a", "2410": "\uff41", "2411": "\uff50", "2412": "\uff4e", "2413": "\uff53", "2414": "\uff43", "2415": "\uff4d", "2416": "\u5939", "2417": "\u6376", "2418": "\uff2e", "2419": "\uff4f", "2420": "\uff29", "2421": "\uff48", "2422": "\u77aa", "2423": "\u8170", "2424": "\u819d", "2425": "\u5f2f", "2426": "\u5f27", "2427": "\u555c", "2428": "\u996e", "2429": "\u7f50", "2430": "\u5821", "2431": "\u9985", "2432": "\u7389", "2433": "\u67dc", "2434": "\u5eca", "2435": "\u88d9", "2436": "\u75b2", "2437": "\u7eb5", "2438": "\u9713", "2439": "\u5320", "2440": "\u7578", "2441": "\u9c81", "2442": "\u574d", "2443": "\u5e06", "2444": "\u9504", "2445": "\u4fd1", "2446": "\u55e4", "2447": "\u5632", "2448": "\u8346", "2449": "\u66d9", "2450": "\u4f57", "2451": "\u65a7", "2452": "\u8327", "2453": "\u50fb", "2454": "\u52fe", "2455": "\u7ae3", "2456": "\u5acc", "2457": "\u5256", "2458": "\u79fb", "2459": "\u5ac1", "2460": "\u7aed", "2461": "\u8328", "2462": "\u8574", "2463": "\u6043", "2464": "\u7ffc", "2465": "\u5362", "2466": "\u9610", "2467": "\u6414", "2468": "\u672d", "2469": "\u97e9", "2470": "\u62df", "2471": "\u5703", "2472": "\u70db", "2473": "\u895f", "2474": "\u6069", "2475": "\u5306", "2476": "\u699c", "2477": "\u51cc", "2478": "\u70d9", "2479": "\u53d9", "2480": "\u6653", "2481": "\u6402", "2482": "\u853c", "2483": "\u758f", "2484": "\u535c", "2485": "\u68a7", "2486": "\u9e64", "2487": "\u772f", "2488": "\u8350", "2489": "\u51a5", "2490": "\u8fa8", "2491": "\u8dfb", "2492": "\u7a3d", "2493": "\u5ddd", "2494": "\u5ef7", "2495": "\uff2c", "2496": "\uff27", "2497": "\u70f7", "2498": "\u9187", "2499": "\u6c22", "2500": "\u6e24", "2501": "\u5676", "2502": "\u6ed1", "2503": "\u904f", "2504": "\u90a6", "2505": "\u6731", "2506": "\u9555", "2507": "\u629b", "2508": "\u7ea4", "2509": "\u64c5", "2510": "\u5784", "2511": "\u7f1a", "2512": "\u786b", "2513": "\u98e8", "2514": "\u629a", "2515": "\u6995", "2516": "\u780c", "2517": "\u8426", "2518": "\u531d", "2519": "\u78a7", "2520": "\u5524", "2521": "\u9e3d", "2522": "\u7eda", "2523": "\u51af", "2524": "\u54f2", "2525": "\u749e", "2526": "\u64c0", "2527": "\u7a20", "2528": "\u54e9", "2529": "\u8d50", "2530": "\u7b77", "2531": "\u5951", "2532": "\u9b3c", "2533": "\u9875", "2534": "\u63c9", "2535": "\u7eb9", "2536": "\u7a3b", "2537": "\u58f3", "2538": "\u9676", "2539": "\u6756", "2540": "\u5300", "2541": "\u5ab3", "2542": "\u552c", "2543": "\u74e3", "2544": "\u809a", "2545": "\u575f", "2546": "\u7b28", "2547": "\u732a", "2548": "\u5151", "2549": "\u74e2", "2550": "\u5962", "2551": "\u4f88", "2552": "\u538c", "2553": "\u7bee", "2554": "\u6fe1", "2555": "\u6cab", "2556": "\u90bb", "2557": "\u7eaf", "2558": "\u6208", "2559": "\u80b4", "2560": "\u562c", "2561": "\u5507", "2562": "\u6084", "2563": "\u6816", "2564": "\u9e20", "2565": "\u9e42", "2566": "\u9e4a", "2567": "\u9e67", "2568": "\u9e2a", "2569": "\u6866", "2570": "\u699b", "2571": "\u67f3", "2572": "\u6749", "2573": "\u6748", "2574": "\u84e6", "2575": "\u6cd3", "2576": "\u8e66", "2577": "\u9a73", "2578": "\u5c91", "2579": "\u8c27", "2580": "\u6652", "2581": "\u6a90", "2582": "\u86db", "2583": "\u7b3c", "2584": "\u5c4f", "2585": "\u5c18", "2586": "\u56a3", "2587": "\u68ad", "2588": "\u5f0b", "2589": "\u55a7", "2590": "\u54d7", "2591": "\u7ef0", "2592": "\u9634", "2593": "\u663c", "2594": "\u6d43", "2595": "\u5598", "2596": "\u9a7c", "2597": "\u5f13", "2598": "\u866c", "2599": "\u9aef", "2600": "\u77cd", "2601": "\u94c4", "2602": "\u5b87", "2603": "\u587e", "2604": "\u859b", "2605": "\u593c", "2606": "\u6f7a", "2607": "\u8be7", "2608": "\u527d", "2609": "\u6842", "2610": "\u7b8d", "2611": "\u4ea9", "2612": "\u5f25", "2613": "\u6c6a", "2614": "\u5140", "2615": "\u94c5", "2616": "\u9edb", "2617": "\u5375", "2618": "\u7ef5", "2619": "\uff4b", "2620": "\uff55", "2621": "\uff47", "2622": "\u658b", "2623": "\u6469", "2624": "\u8f8d", "2625": "\u4f26", "2626": "\u6851", "2627": "\u9ccc", "2628": "\u6247", "2629": "\u626f", "2630": "\u6daf", "2631": "\u5df7", "2632": "\u62b9", "2633": "\u5a11", "2634": "\u601c", "2635": "\u8749", "2636": "\u5d1b", "2637": "\u575b", "2638": "\u9a86", "2639": "\u8db5", "2640": "\u59a8", "2641": "\u62d9", "2642": "\u62d8", "2643": "\u97ad", "2644": "\u9119", "2645": "\u4fdf", "2646": "\u5bc4", "2647": "\u6627", "2648": "\u817a", "2649": "\u7720", "2650": "\u8f85", "2651": "\u7384", "2652": "\u5e16", "2653": "\u63e3", "2654": "\u8c2b", "2655": "\u964b", "2656": "\u7ed8", "2657": "\u7109", "2658": "\u5179", "2659": "\u7948", "2660": "\u8870", "2661": "\u88e8", "2662": "\u5f1b", "2663": "\u8c05", "2664": "\u8046", "2665": "\u6155", "2666": "\u9525", "2667": "\u5bb5", "2668": "\uff3b", "2669": "\uff3d", "2670": "\u949c", "2671": "\u9677", "2672": "\u85fb", "2673": "\u673d", "2674": "\u9f0e", "2675": "\u5a36", "2676": "\u7f62", "2677": "\u89de", "2678": "\u8f74", "2679": "\u71e5", "2680": "\u6d46", "2681": "\u8dcc", "2682": "\u8de4", "2683": "\u5bc7", "2684": "\u6454", "2685": "\u4e58", "2686": "\u643a", "2687": "\u7ece", "2688": "\u53a8", "2689": "\u6cd4", "2690": "\u8721", "2691": "\u6e2d", "2692": "\u6f58", "2693": "\u6fb6", "2694": "\u6e0a", "2695": "\u60e8", "2696": "\u9ebb", "2697": "\u82f9", "2698": "\u60cb", "2699": "\u5937", "2700": "\u58a9", "2701": "\u99a8", "2702": "\u5dfe", "2703": "\u62e2", "2704": "\u63ed", "2705": "\u86cb", "2706": "\u621a", "2707": "\u9881", "2708": "\u8912", "2709": "\u5b5d", "2710": "\u7cbd", "2711": "\u82c7", "2712": "\u7076", "2713": "\u6c24", "2714": "\u6c32", "2715": "\u8155", "2716": "\u7fe0", "2717": "\u952f", "2718": "\u83d6", "2719": "\u84b2", "2720": "\u8d63", "2721": "\u8d2c", "2722": "\u8c2c", "2723": "\u7422", "2724": "\u5b99", "2725": "\u517d", "2726": "\u6bd3", "2727": "\u7199", "2728": "\u586b", "2729": "\u51f8", "2730": "\u77a9", "2731": "\u5c39", "2732": "\u6492", "2733": "\u7fa1", "2734": "\u533e", "2735": "\u4faf", "2736": "\u5e99", "2737": "\u6c10", "2738": "\u8d60", "2739": "\u796d", "2740": "\u7940", "2741": "\u9e3f", "2742": "\u80ba", "2743": "\u8151", "2744": "\u916c", "2745": "\u94a6", "2746": "\u5669", "2747": "\u67ab", "2748": "\u576a", "2749": "\u5189", "2750": "\u5188", "2751": "\u90aa", "2752": "\u6076", "2753": "\u6bbf", "2754": "\u773a", "2755": "\u6dcc", "2756": "\u6593", "2757": "\u5ce6", "2758": "\u2463", "2759": "\u2462", "2760": "\u759d", "2761": "\u80c3", "2762": "\u7f13", "2763": "\u7696", "2764": "\u7800", "2765": "\u6276", "2766": "\u7f5a", "2767": "\u5de9", "2768": "\u76d7", "2769": "\u725f", "2770": "\u766b", "2771": "\u75eb", "2772": "\u7433", "2773": "\u75f0", "2774": "\u795b", "2775": "\u6de4", "2776": "\u809d", "2777": "\u80be", "2778": "\u866b", "2779": "\u970d", "2780": "\u808c", "2781": "\u5815", "2782": "\u6063", "2783": "\u840e", "2784": "\u9761", "2785": "\u82df", "2786": "\u8bff", "2787": "\u6577", "2788": "\u884d", "2789": "\u6020", "2790": "\u788d", "2791": "\u8c00", "2792": "\u9970", "2793": "\u7792", "2794": "\u50da", "2795": "\u7f54", "2796": "\u65e8", "2797": "\u6396", "2798": "\u9ad3", "2799": "\u8e81", "2800": "\u65a5", "2801": "\u6291", "2802": "\u7fc1", "2803": "\u60d5", "2804": "\u9888", "2805": "\u6850", "2806": "\u60f0", "2807": "\u94ed", "2808": "\u50f5", "2809": "\u60d8", "2810": "\u6052", "2811": "\u6d45", "2812": "\u5026", "2813": "\u5cb3", "2814": "\u6109", "2815": "\u7941", "2816": "\u7816", "2817": "\u5ce8", "2818": "\u8038", "2819": "\u5792", "2820": "\u693d", "2821": "\u56f1", "2822": "\u9542", "2823": "\u5ba0", "2824": "\u5496", "2825": "\u5561", "2826": "\u955b", "2827": "\u71b9", "2828": "\u5cd9", "2829": "\u938f", "2830": "\u5f6d", "2831": "\u5c27", "2832": "\u745f", "2833": "\u82a6", "2834": "\u814a", "2835": "\u6cfc", "2836": "\uff33", "2837": "\u66fc", "2838": "\u77f6", "2839": "\u5d0e", "2840": "\u55e3", "2841": "\u94e8", "2842": "\u6614", "2843": "\u70b3", "2844": "\u80ae", "2845": "\u5783", "2846": "\u573e", "2847": "\u60ee", "2848": "\u659c", "2849": "\u6ee5", "2850": "\u717d", "2851": "\u5a9a", "2852": "\u96fe", "2853": "\u7f2d", "2854": "\u4f51", "2855": "\u7ca4", "2856": "\u522e", "2857": "\u88ad", "2858": "\u6cc4", "2859": "\u94a9", "2860": "\u7b0b", "2861": "\u996f", "2862": "\u5220", "2863": "\u715e", "2864": "\u8e35", "2865": "\u6c88", "2866": "\uff31", "2867": "\u9aa4", "2868": "\u8f7c", "2869": "\u9675", "2870": "\u660c", "2871": "\u7f03", "2872": "\u6124", "2873": "\u90ed", "2874": "\u6cca", "2875": "\u8367", "2876": "\u7280", "2877": "\u57a6", "2878": "\u5c6f", "2879": "\u7095", "2880": "\u8d2e", "2881": "\u6c28", "2882": "\u79f8", "2883": "\u79c6", "2884": "\u6c2e", "2885": "\u78b1", "2886": "\u84b8", "2887": "\u857e", "2888": "\u7ce0", "2889": "\u5398", "2890": "\u7261", "2891": "\u94e7", "2892": "\u8019", "2893": "\u94f5", "2894": "\u9493", "2895": "\u9e35", "2896": "\u9cb6", "2897": "\u9cb3", "2898": "\u82b9", "2899": "\u6a31", "2900": "\u841d", "2901": "\u838e", "2902": "\u88d5", "2903": "\u6c90", "2904": "\u757f", "2905": "\u5885", "2906": "\u5bb8", "2907": "\u5fa1", "2908": "\u516e", "2909": "\u62c2", "2910": "\u6787", "2911": "\u6777", "2912": "\u7b50", "2913": "\u8386", "2914": "\u5830", "2915": "\u502a", "2916": "\u819c", "2917": "\u7ad6", "2918": "\u95f8", "2919": "\u8eba", "2920": "\u94b5", "2921": "\u5415", "2922": "\u532e", "2923": "\u72d0", "2924": "\u65ec", "2925": "\u67a3", "2926": "\u68a8", "2927": "\u8d41", "2928": "\u77e2", "2929": "\u6e1d", "2930": "\u83c5", "2931": "\u7855", "2932": "\u961c", "2933": "\u676d", "2934": "\u87ba", "2935": "\u62e7", "2936": "\u9738", "2937": "\u9051", "2938": "\u543e", "2939": "\u8d61", "2940": "\u5c38", "2941": "\u6dee", "2942": "\u5a7f", "2943": "\u8f69", "2944": "\u4ed7", "2945": "\u8c4c", "2946": "\u8c46", "2947": "\u997c", "2948": "\u97ec", "2949": "\u5b5f", "2950": "\u5d2e", "2951": "\u6cb8", "2952": "\u6cad", "2953": "\u8d6b", "2954": "\u6d9f", "2955": "\u6ce3", "2956": "\u6400", "2957": "\u98a4", "2958": "\u62ce", "2959": "\u6035", "2960": "\u5c60", "2961": "\u622e", "2962": "\u5265", "2963": "\u62f4", "2964": "\u83b2", "2965": "\u7a14", "2966": "\u7d2b", "2967": "\u6d78", "2968": "\u637a", "2969": "\u81ed", "2970": "\u59da", "2971": "\u90b5", "2972": "\u532a", "2973": "\u8d54", "2974": "\u6853", "2975": "\u9e7f", "2976": "\u5c65", "2977": "\u6905", "2978": "\u503a", "2979": "\u8bbc", "2980": "\u8096", "2981": "\u6566", "2982": "\u63fd", "2983": "\u5fd6", "2984": "\u60eb", "2985": "\u90b9", "2986": "\u9e9f", "2987": "\u783a", "2988": "\u9716", "2989": "\u501a", "2990": "\u6655", "2991": "\u5435", "2992": "\u5543", "2993": "\u8e31", "2994": "\u964c", "2995": "\u9894", "2996": "\u541e", "2997": "\u6252", "2998": "\u7f15", "2999": "\u828d", "3000": "\u5cea", "3001": "\u5201", "3002": "\u75ab", "3003": "\u5bfa", "3004": "\u8e1e", "3005": "\u5d16", "3006": "\u84df", "3007": "\u6021", "3008": "\u61a9", "3009": "\u7f24", "3010": "\u4ed3", "3011": "\u50e7", "3012": "\u6da7", "3013": "\u6f8e", "3014": "\u6e43", "3015": "\u78c5", "3016": "\u7934", "3017": "\u5d99", "3018": "\u5ccb", "3019": "\u8236", "3020": "\u6daa", "3021": "\u78cb", "3022": "\u7426", "3023": "\u51b6", "3024": "\u5609", "3025": "\u81a8", "3026": "\u80c0", "3027": "\u65f7", "3028": "\u8231", "3029": "\u8238", "3030": "\u917f", "3031": "\u8e2a", "3032": "\u680b", "3033": "\u566c", "3034": "\u7435", "3035": "\u7436", "3036": "\u906e", "3037": "\u632a", "3038": "\u9091", "3039": "\u7cb9", "3040": "\u8d81", "3041": "\u8fdf", "3042": "\u9965", "3043": "\u25cf", "3044": "\u7428", "3045": "\u94fe", "3046": "\u6795", "3047": "\u67de", "3048": "\u6dd1", "3049": "\u8e74", "3050": "\u5e7c", "3051": "\u745e", "3052": "\u8339", "3053": "\u9882", "3054": "\u9f9f", "3055": "\u9acb", "3056": "\u80a2", "3057": "\u97e7", "3058": "\u5c3f", "3059": "\u80aa", "3060": "\u80d6", "3061": "\u533f", "3062": "\u7d6e", "3063": "\u53e8", "3064": "\u8f99", "3065": "\uff36", "3066": "\u78c1", "3067": "\u8f91", "3068": "\u88f3", "3069": "\u9e5c", "3070": "\u62f7", "3071": "\u8d1d", "3072": "\u7a9d", "3073": "\u4ea2", "3074": "\u817b", "3075": "\u537f", "3076": "\u9ae6", "3077": "\u83a0", "3078": "\u82ae", "3079": "\u59dc", "3080": "\u52d2", "3081": "\u25b2", "3082": "\u25cb", "3083": "\u962a", "3084": "\uff25", "3085": "\u7f14", "3086": "\u9e4f", "3087": "\u82ac", "3088": "\u7f05", "3089": "\u7538", "3090": "\u631d", "3091": "\u8fc4", "3092": "\u5bd3", "3093": "\u74f7", "3094": "\u82d1", "3095": "\u6f47", "3096": "\u9ed4", "3097": "\u9e45", "3098": "\u66a8", "3099": "\u5c9a", "3100": "\u6deb", "3101": "\u79fd", "3102": "\u66dd", "3103": "\u5d4a", "3104": "\u6b9a", "3105": "\u55dc", "3106": "\u635e", "3107": "\u8c23", "3108": "\u840c", "3109": "\u70d8", "3110": "\u584c", "3111": "\u9975", "3112": "\u53a6", "3113": "\u88f9", "3114": "\u78be", "3115": "\u62f1", "3116": "\u6e23", "3117": "\u658c", "3118": "\u6ca5", "3119": "\u6273", "3120": "\u903e", "3121": "\u9ca4", "3122": "\u7c07", "3123": "\u9a7f", "3124": "\u8f96", "3125": "\u6f33", "3126": "\u60df", "3127": "\u8859", "3128": "\u763c", "3129": "\u7572", "3130": "\u7cef", "3131": "\u5be8", "3132": "\u8471", "3133": "\u7a46", "3134": "\uff54", "3135": "\uff52", "3136": "\u72d7", "3137": "\u5ff1", "3138": "\u96b6", "3139": "\u4fca", "3140": "\u7bc6", "3141": "\u9521", "3142": "\u68cd", "3143": "\u9601", "3144": "\u819b", "3145": "\u9edd", "3146": "\u6572", "3147": "\u6760", "3148": "\u759a", "3149": "\u7f2e", "3150": "\u4fcf", "3151": "\u5986", "3152": "\u70c1", "3153": "\u7c41", "3154": "\u8bcf", "3155": "\u915d", "3156": "\u79c9", "3157": "\u8297", "3158": "\u4f83", "3159": "\u2236", "3160": "\u865e", "3161": "\u9a9a", "3162": "\u8759", "3163": "\u8760", "3164": "\u69b7", "3165": "\u9e47", "3166": "\u8206", "3167": "\u662d", "3168": "\u77ac", "3169": "\u9b45", "3170": "\u645e", "3171": "\u7fd4", "3172": "\u6df9", "3173": "\u789f", "3174": "\u5564", "3175": "\u853d", "3176": "\u7ea3", "3177": "\u6177", "3178": "\u67c4", "3179": "\u51ff", "3180": "\u52ab", "3181": "\u8944", "3182": "\u6a0a", "3183": "\u718a", "3184": "\u998d", "3185": "\u9a6e", "3186": "\u58d1", "3187": "\u94dd", "3188": "\u9492", "3189": "\u79b9", "3190": "\u8702", "3191": "\u9600", "3192": "\u78b3", "3193": "\u708a", "3194": "\u7ee5", "3195": "\u77d7", "3196": "\u5e9e", "3197": "\u711a", "3198": "\u82bd", "3199": "\u5be5", "3200": "\u9570", "3201": "\u94f2", "3202": "\u5858", "3203": "\u80da", "3204": "\u728a", "3205": "\u679a", "3206": "\u94be", "3207": "\u78f7", "3208": "\u6e89", "3209": "\u4e18", "3210": "\u61f5", "3211": "\u5e3c", "3212": "\u804b", "3213": "\u94dc", "3214": "\u5d4b", "3215": "\u61b7", "3216": "\u9699", "3217": "\u5baa", "3218": "\u8521", "3219": "\u62a8", "3220": "\u8c34", "3221": "\u718f", "3222": "\u6151", "3223": "\u777d", "3224": "\u7fe9", "3225": "\u8eac", "3226": "\u6808", "3227": "\u5ced", "3228": "\u5bdd", "3229": "\u64ac", "3230": "\u5c96", "3231": "\u6dc0", "3232": "\u6da9", "3233": "\u57c2", "3234": "\u7eca", "3235": "\u873f", "3236": "\u8712", "3237": "\u9992", "3238": "\u5406", "3239": "\u8d4c", "3240": "\u627c", "3241": "\u674f", "3242": "\u6817", "3243": "\u7fc5", "3244": "\u7ef8", "3245": "\u5e1a", "3246": "\u5580", "3247": "\u5e62", "3248": "\u77ee", "3249": "\u5608", "3250": "\u8e22", "3251": "\u4e4d", "3252": "\u560e", "3253": "\u8fc2", "3254": "\u8428", "3255": "\u6f13", "3256": "\u5455", "3257": "\u70eb", "3258": "\u6405", "3259": "\u62cc", "3260": "\u9165", "3261": "\u5ed3", "3262": "\u51f9", "3263": "\u5ac2", "3264": "\u60f4", "3265": "\u848b", "3266": "\u55d2", "3267": "\u84c9", "3268": "\u76f9", "3269": "\u8d48", "3270": "\u607b", "3271": "\u5014", "3272": "\u5a1f", "3273": "\u5a74", "3274": "\u5582", "3275": "\u9640", "3276": "\u7470", "3277": "\u5e7a", "3278": "\u5a75", "3279": "\u548f", "3280": "\u6b87", "3281": "\u85c9", "3282": "\u8d1e", "3283": "\u6292", "3284": "\u745b", "3285": "\u7c27", "3286": "\u80eb", "3287": "\u6d5c", "3288": "\u5e15", "3289": "\u8482", "3290": "\u68b3", "3291": "\u5636", "3292": "\u70ab", "3293": "\u5671", "3294": "\u575e", "3295": "\u900a", "3296": "\u6487", "3297": "\u5567", "3298": "\u5a1c", "3299": "\u77bf", "3300": "\u7574", "3301": "\u6a71", "3302": "\u8292", "3303": "\u88f8", "3304": "\u8389", "3305": "\u57e0", "3306": "\u9642", "3307": "\u8006", "3308": "\u5154", "3309": "\u736d", "3310": "\u67da", "3311": "\u8549", "3312": "\u57d4", "3313": "\u8354", "3314": "\u8110", "3315": "\u6a59", "3316": "\u6cbc", "3317": "\u5251", "3318": "\u879f", "3319": "\u6912", "3320": "\u8695", "3321": "\u814c", "3322": "\uff0b", "3323": "\u8d4a", "3324": "\u7edb", "3325": "\u690e", "3326": "\u6361", "3327": "\u57a2", "3328": "\u5d4c", "3329": "\u7efd", "3330": "\u51cb", "3331": "\u8e1d", "3332": "\u7741", "3333": "\u5760", "3334": "\u504e", "3335": "\u5203", "3336": "\u592d", "3337": "\u868c", "3338": "\u55bb", "3339": "\u5e18", "3340": "\u6c82", "3341": "\u5e37", "3342": "\u82f7", "3343": "\u8c0e", "3344": "\u7fdf", "3345": "\u95fd", "3346": "\u7a98", "3347": "\u6876", "3348": "\u8c19", "3349": "\u839c", "3350": "\u6c3d", "3351": "\u998b", "3352": "\u809b", "3353": "\u7f06", "3354": "\u69fd", "3355": "\u9508", "3356": "\u5c94", "3357": "\u8517", "3358": "\u68d8", "3359": "\u9893", "3360": "\u6ca7", "3361": "\u795c", "3362": "\u4ed5", "3363": "\u74ee", "3364": "\u94a5", "3365": "\u5319", "3366": "\u64c2", "3367": "\u606d", "3368": "\u8d3e", "3369": "\u968b", "3370": "\u90b1", "3371": "\u6cf5", "3372": "\u692d", "3373": "\u9661", "3374": "\u8881", "3375": "\u9647", "3376": "\u7a96", "3377": "\u7620", "3378": "\u8f90", "3379": "\u62fe", "3380": "\u4fa6", "3381": "\u8beb", "3382": "\u901b", "3383": "\u5b7d", "3384": "\u9e43", "3385": "\u852b", "3386": "\u547b", "3387": "\u5349", "3388": "\u634d", "3389": "\u82ad", "3390": "\u846c", "3391": "\u7e82", "3392": "\u8bc3", "3393": "\u954c", "3394": "\u7f38", "3395": "\u7ca5", "3396": "\u8be1", "3397": "\u56f9", "3398": "\u5704", "3399": "\u6a84", "3400": "\u50bb", "3401": "\u620e", "3402": "\u636d", "3403": "\u9616", "3404": "\u8c82", "3405": "\u8d3b", "3406": "\u4fef", "3407": "\u6249", "3408": "\u94b3", "3409": "\u6c9b", "3410": "\u81c6", "3411": "\u79ba", "3412": "\u8654", "3413": "\u67ef", "3414": "\u5228", "3415": "\u589f", "3416": "\u59fb", "3417": "\u6d85", "3418": "\u70bd", "3419": "\u6096", "3420": "\u96f9", "3421": "\u6d9d", "3422": "\u4e9f", "3423": "\u3008", "3424": "\u3009", "3425": "\u6dae", "3426": "\u85aa", "3427": "\u6e83", "3428": "\u75ca", "3429": "\u5384", "3430": "\u5352", "3431": "\u94c3", "3432": "\u54aa", "3433": "\u7b5b", "3434": "\u594e", "3435": "\u6dde", "3436": "\u6c7e", "3437": "\u8335", "3438": "\u6556", "3439": "\u78ca", "3440": "\u70e8", "3441": "\u6590", "3442": "\u82aa", "3443": "\u79d2", "3444": "\u971e", "3445": "\u7aa5", "3446": "\u7256", "3447": "\u840d", "3448": "\u8556", "3449": "\u5bc5", "3450": "\u5484", "3451": "\u9ab8", "3452": "\u4e52", "3453": "\u4e53", "3454": "\u6fe0", "3455": "\u98d9", "3456": "\u5308", "3457": "\u808b", "3458": "\u9f7f", "3459": "\u8dd7", "3460": "\u8dbe", "3461": "\u70fd", "3462": "\u4f8f", "3463": "\u9530", "3464": "\u8b6c", "3465": "\u74a7", "3466": "\u8301", "3467": "\u81b3", "3468": "\u7490", "3469": "\u73cf", "3470": "\u709c", "3471": "\u73c0", "3472": "\u5bf0", "3473": "\u5f17", "3474": "\u61ca", "3475": "\u00d7", "3476": "\u4eb3", "3477": "\u8a93", "3478": "\u9ebe", "3479": "\u8427", "3480": "\uff32", "3481": "\u59ca", "3482": "\u7ff0", "3483": "\u7480", "3484": "\u74a8", "3485": "\u8273", "3486": "\u5043", "3487": "\u6bcb", "3488": "\u948a", "3489": "\u7aff", "3490": "\u8475", "3491": "\u831c", "3492": "\u8db4", "3493": "\u6f78", "3494": "\u742a", "3495": "\u6656", "3496": "\u5195", "3497": "\u9523", "3498": "\u6960", "3499": "\u839e", "3500": "\u7fbd", "3501": "\u8be0", "3502": "\u8a79", "3503": "\u83b9", "3504": "\u5af1", "3505": "\u9aa7", "3506": "\u8018", "3507": "\u8e4a", "3508": "\u5029", "3509": "\u7396", "3510": "\u745c", "3511": "\u73c8", "3512": "\u8ff8", "3513": "\u9083", "3514": "\u5b17", "3515": "\u69bb", "3516": "\u5b71", "3517": "\u762b", "3518": "\u75f9", "3519": "\u61a8", "3520": "\u4e98", "3521": "\u5486", "3522": "\u54ee", "3523": "\u868a", "3524": "\u6016", "3525": "\u761f", "3526": "\u5ae9", "3527": "\u7405", "3528": "\u740a", "3529": "\u6ec1", "3530": "\u83f1", "3531": "\u5a32", "3532": "\u8174", "3533": "\u71e7", "3534": "\u9617", "3535": "\u7455", "3536": "\u7011", "3537": "\u9131", "3538": "\u7b60", "3539": "\u803f", "3540": "\u8c1b", "3541": "\u6026", "3542": "\u9eef", "3543": "\u9522", "3544": "\u726f", "3545": "\u5321", "3546": "\u6e4d", "3547": "\u6714", "3548": "\u8587", "3549": "\u5d14", "3550": "\u6d19", "3551": "\u57c3", "3552": "\u5a05", "3553": "\u61ff", "3554": "\u6c55", "3555": "\u4f36", "3556": "\u63b7", "3557": "\u6cd7", "3558": "\u8042", "3559": "\u660a", "3560": "\u5146", "3561": "\u5e1b", "3562": "\u988d", "3563": "\u81e7", "3564": "\u5b6a", "3565": "\u94c9", "3566": "\u52cb", "3567": "\u817c", "3568": "\u8146", "3569": "\u7a1a", "3570": "\u9cb8", "3571": "\u8c5a", "3572": "\u61a7", "3573": "\u61ac", "3574": "\u821c", "3575": "\u5a34", "3576": "\u5583", "3577": "\u69ad", "3578": "\uff59", "3579": "\uff46", "3580": "\uff42", "3581": "\uff4c", "3582": "\u8821", "3583": "\u604d", "3584": "\u730e", "3585": "\u973e", "3586": "\u98a0", "3587": "\u846b", "3588": "\u8df7", "3589": "\u888d", "3590": "\u6342", "3591": "\u988a", "3592": "\u6eaf", "3593": "\u6dfc", "3594": "\u94b0", "3595": "\u816d", "3596": "\u6c81", "3597": "\u79c3", "3598": "\u8c1c", "3599": "\u72d9", "3600": "\u541d", "3601": "\u53a2", "3602": "\u8e6c", "3603": "\u572d", "3604": "\u2461", "3605": "\u2460", "3606": "\u778e", "3607": "\u78d5", "3608": "\u63ba", "3609": "\u5f29", "3610": "\u7ec5", "3611": "\u4fa5", "3612": "\u62ed", "3613": "\u7130", "3614": "\u52df", "3615": "\u6363", "3616": "\u8087", "3617": "\u72ac", "3618": "\u8bb6", "3619": "\u7a92", "3620": "\u6495", "3621": "\u5f66", "3622": "\u5742", "3623": "\u7ed2", "3624": "\u9102", "3625": "\uff2d", "3626": "\u9c7f", "3627": "\u5ab2", "3628": "\u4ea8", "3629": "\u9a81", "3630": "\u97e6", "3631": "\u8dc6", "3632": "\u5f6c", "3633": "\u8c0d", "3634": "\u916a", "3635": "\u7fcc", "3636": "\u5f9c", "3637": "\u5f89", "3638": "\u7949", "3639": "\u695e", "3640": "\u8205", "3641": "\u4e56", "3642": "\u8611", "3643": "\u83c7", "3644": "\u6854", "3645": "\u67d1", "3646": "\u62e3", "3647": "\u60b8", "3648": "\u8f97", "3649": "\u7785", "3650": "\u6dc5", "3651": "\u9576", "3652": "\u8f6b", "3653": "\u7ff3", "3654": "\u7b1b", "3655": "\u8616", "3656": "\u8885", "3657": "\u6f3e", "3658": "\u70af", "3659": "\u7cb2", "3660": "\u86f0", "3661": "\u6073", "3662": "\u7762", "3663": "\u7a57", "3664": "\u545c", "3665": "\u762a", "3666": "\u9017", "3667": "\uff44", "3668": "\u2500", "3669": "\u2510", "3670": "\u2502", "3671": "\u2518", "3672": "\u6bb4", "3673": "\u7f69", "3674": "\u970f", "3675": "\u4fa0", "3676": "\u8f76", "3677": "\u701b", "3678": "\u7977", "3679": "\uff58", "3680": "\u82af", "3681": "\u6664", "3682": "\u9551", "3683": "\u96c7", "3684": "\u7845", "3685": "\u6773", "3686": "\u64d8", "3687": "\u6eba", "3688": "\u759f", "3689": "\u7316", "3690": "\u7357", "3691": "\u94e2", "3692": "\u568f", "3693": "\u8fed", "3694": "\u680e", "3695": "\u6813", "3696": "\u6c1f", "3697": "\u69df", "3698": "\u6846", "3699": "\u6c26", "3700": "\u9c8d", "3701": "\u6c2f", "3702": "\u9536", "3703": "\u6a80", "3704": "\u598a", "3705": "\u5a20", "3706": "\u9176", "3707": "\u6ccc", "3708": "\u6ca6", "3709": "\u4e5e", "3710": "\u6b83", "3711": "\u7abf", "3712": "\u6772", "3713": "\u6dc4", "3714": "\u4f7c", "3715": "\u4fae", "3716": "\u6c30", "3717": "\u80fa", "3718": "\u94a0", "3719": "\u5944", "3720": "\u5993", "3721": "\u5a3c", "3722": "\u7f09", "3723": "\u5978", "3724": "\u94e4", "3725": "\u6e25", "3726": "\u7f2a", "3727": "\u6c76", "3728": "\u4f1e", "3729": "\u9668", "3730": "\u90e1", "3731": "\u98d3", "3732": "\u642a", "3733": "\u67ff", "3734": "\u9175", "3735": "\u6c41", "3736": "\u7830", "3737": "\u837c", "3738": "\u6dc7", "3739": "\u7784", "3740": "\u5a6a", "3741": "\u914b", "3742": "\u82b8", "3743": "\u954d", "3744": "\u9549", "3745": "\u83c1", "3746": "\u868b", "3747": "\u8747", "3748": "\u4ea5", "3749": "\u548e", "3750": "\u5578", "3751": "\u96cc", "3752": "\uff35", "3753": "\u8737", "3754": "\u543b", "3755": "\u9539", "3756": "\u871a", "3757": "\u5b95", "3758": "\u96bd", "3759": "\u5cb1", "3760": "\u7eb6", "3761": "\u7852", "3762": "\u9088", "3763": "\u80f1", "3764": "\u77b3", "3765": "\u8f95", "3766": "\u4fac", "3767": "\u71ce", "3768": "\u9cd5", "3769": "\u6c50", "3770": "\u9541", "3771": "\u6eb4", "3772": "\u94c0", "3773": "\u94b4", "3774": "\u696b", "3775": "\uff37", "3776": "\u9cb1", "3777": "\u6bd7", "3778": "\u6c5e", "3779": "\u950c", "3780": "\u94c2", "3781": "\u75cd", "3782": "\u72c4", "3783": "\u57a0", "3784": "\u8774", "3785": "\u5323", "3786": "\u731d", "3787": "\u536f", "3788": "\u670a", "3789": "\u520d", "3790": "\u9abc", "3791": "\u68fa", "3792": "\u7a9f", "3793": "\u63c6", "3794": "\u5b5a", "3795": "\u54c7", "3796": "\u5a29", "3797": "\u83e0", "3798": "\u72c8", "3799": "\u9512", "3800": "\u94db", "3801": "\u72f1", "3802": "\u6467", "3803": "\u9e26", "3804": "\u5deb", "3805": "\u8bdb", "3806": "\u6f7c", "3807": "\u5958", "3808": "\uff5a", "3809": "\u67b8", "3810": "\u675e", "3811": "\u68a2", "3812": "\u82e3", "3813": "\u56e4", "3814": "\u83b4", "3815": "\u830e", "3816": "\u836c", "3817": "\u693f", "3818": "\u7f28", "3819": "\u835e", "3820": "\u5197", "3821": "\u5fff", "3822": "\u7afa", "3823": "\u7118", "3824": "\u7329", "3825": "\u5d3d", "3826": "\u5d34", "3827": "\u7c38", "3828": "\u6d4f", "3829": "\u75a1", "3830": "\u7fee", "3831": "\uff39", "3832": "\u7638", "3833": "\u8ddb", "3834": "\u5983", "3835": "\u5f99", "3836": "\u8725", "3837": "\u7766", "3838": "\u8e0a", "3839": "\u753a", "3840": "\u6448", "3841": "\u84bf", "3842": "\u5f5d", "3843": "\u88f4", "3844": "\u6986", "3845": "\u81ba", "3846": "\u5c09", "3847": "\u5b5c", "3848": "\u5ad6", "3849": "\u67ad", "3850": "\u6bd9", "3851": "\u5a25", "3852": "\u5a9b", "3853": "\u7c7c", "3854": "\u7476", "3855": "\u8343", "3856": "\u886b", "3857": "\u90a2", "3858": "\u6055", "3859": "\u8845", "3860": "\u9074", "3861": "\u6538", "3862": "\u6954", "3863": "\u901e", "3864": "\u6684", "3865": "\u7bb4", "3866": "\u7487", "3867": "\u66b9", "3868": "\u94ce", "3869": "\u7bd9", "3870": "\u7f79", "3871": "\u90b8", "3872": "\u6e44", "3873": "\u741b", "3874": "\u7bea", "3875": "\u60bc", "3876": "\u776b", "3877": "\u962e", "3878": "\u6cf8", "3879": "\u9499", "3880": "\u7119", "3881": "\u9753", "3882": "\u6525", "3883": "\u6410", "3884": "\u6b6a", "3885": "\u5351", "3886": "\u7337", "3887": "\u6ed5", "3888": "\u9540", "3889": "\u867e", "3890": "\u768e", "3891": "\u5b73", "3892": "\u75c9", "3893": "\u631b", "3894": "\u7c7d", "3895": "\u77b0", "3896": "\u6fd1", "3897": "\u7837", "3898": "\u952d", "3899": "\u52fa", "3900": "\u7cb1", "3901": "\u915a", "3902": "\u87f9", "3903": "\u86b6", "3904": "\u9c88", "3905": "\u8e69", "3906": "\u6f88", "3907": "\uff56", "3908": "\u53f1", "3909": "\u54a4", "3910": "\u70e4", "3911": "\u85b0", "3912": "\u82a5", "3913": "\u5364", "3914": "\u62ee", "3915": "\u996a", "3916": "\u8757", "3917": "\u9cc5", "3918": "\u7096", "3919": "\u79e7", "3920": "\u9f3e", "3921": "\u7b95", "3922": "\u79e4", "3923": "\u818a", "3924": "\u55e8", "3925": "\u5c41", "3926": "\u9528", "3927": "\u78d9", "3928": "\u5657", "3929": "\u54e7", "3930": "\u5693", "3931": "\u553e", "3932": "\u55f7", "3933": "\u8bb3", "3934": "\u95fa", "3935": "\u77a0", "3936": "\u94a7", "3937": "\u6977", "3938": "\u8bf2", "3939": "\u5b7a", "3940": "\u4f27", "3941": "\u7b19", "3942": "\u57ad", "3943": "\u5ce5", "3944": "\u5d58", "3945": "\u9143", "3946": "\u783b", "3947": "\u90f4", "3948": "\u8012", "3949": "\u9704", "3950": "\u78d0", "3951": "\u5c79", "3952": "\u9977", "3953": "\u6d6f", "3954": "\u5f01", "3955": "\u5e10", "3956": "\u8d32", "3957": "\u7c9f", "3958": "\uff0a", "3959": "\u74e4", "3960": "\u80e4", "3961": "\u8299", "3962": "\u5bd0", "3963": "\u5919", "3964": "\u8e42", "3965": "\u8e8f", "3966": "\u68e0", "3967": "\u6800", "3968": "\u7bf1", "3969": "\u550f", "3970": "\u5618", "3971": "\u9e33", "3972": "\u9e2f", "3973": "\u9082", "3974": "\u9005", "3975": "\u9e3e", "3976": "\u4fe6", "3977": "\u8fe2", "3978": "\u6d52", "3979": "\u9739", "3980": "\u96f3", "3981": "\u5f3c", "3982": "\u9a9e", "3983": "\u8d4e", "3984": "\u7b1e", "3985": "\u8888", "3986": "\u88df", "3987": "\u5b40", "3988": "\u9611", "3989": "\u59ae", "3990": "\u8d66", "3991": "\u75ea", "3992": "\u8e7f", "3993": "\u7ee2", "3994": "\u7bab", "3995": "\u7410", "3996": "\u6014", "3997": "\u60da", "3998": "\u7985", "3999": "\u556a", "4000": "\u8214", "4001": "\u81bb", "4002": "\u7c0c", "4003": "\u8813", "4004": "\u8f71", "4005": "\u8e6d", "4006": "\u545b", "4007": "\u6da4", "4008": "\u91c9", "4009": "\u9503", "4010": "\u5480", "4011": "\u7729", "4012": "\u6c69", "4013": "\u76b4", "4014": "\u7fe6", "4015": "\u69c1", "4016": "\u7b3a", "4017": "\u6a1f", "4018": "\u6a8e", "4019": "\u5dc5", "4020": "\u4ede", "4021": "\u4f6c", "4022": "\u7728", "4023": "\u64de", "4024": "\u7b03", "4025": "\u6289", "4026": "\u779f", "4027": "\u5c49", "4028": "\u6c93", "4029": "\u5fd0", "4030": "\u5fd1", "4031": "\u500f", "4032": "\u52be", "4033": "\u795f", "4034": "\u9602", "4035": "\u7ef7", "4036": "\u69a8", "4037": "\u8c06", "4038": "\u51db", "4039": "\u8700", "4040": "\u8892", "4041": "\u56da", "4042": "\u9e2b", "4043": "\u6ebd", "4044": "\u59a9", "4045": "\u72b7", "4046": "\u9609", "4047": "\u88d4", "4048": "\u7ead", "4049": "\u5420", "4050": "\u905b", "4051": "\u86ee", "4052": "\u577b", "4053": "\u4f63", "4054": "\u9cd6", "4055": "\u7ee3", "4056": "\u80f3", "4057": "\u80ef", "4058": "\u5395", "4059": "\u6805", "4060": "\u659f", "4061": "\u608c", "4062": "\u6518", "4063": "\u63a3", "4064": "\u8098", "4065": "\u5811", "4066": "\u73ab", "4067": "\u51bc", "4068": "\u7691", "4069": "\u830f", "4070": "\u9ccd", "4071": "\u9036", "4072": "\u8fe4", "4073": "\u88fe", "4074": "\u86a4", "4075": "\u5ae6", "4076": "\u9e6d", "4077": "\u7ee6", "4078": "\u8718", "4079": "\u71a0", "4080": "\u85d3", "4081": "\u8717", "4082": "\u7f31", "4083": "\u7efb", "4084": "\u60af", "4085": "\u821b", "4086": "\u7736", "4087": "\u6115", "4088": "\u7f1c", "4089": "\u8e44", "4090": "\u56ff", "4091": "\u9798", "4092": "\u602f", "4093": "\u7ff1", "4094": "\u8e14", "4095": "\u8dcb", "4096": "\u51a2", "4097": "\u6988", "4098": "\u6ca4", "4099": "\u83bd", "4100": "\u5025", "4101": "\u506c", "4102": "\u7078", "4103": "\u6df3", "4104": "\u6dd6", "4105": "\u82a8", "4106": "\u9f9a", "4107": "\u6615", "4108": "\u94cb", "4109": "\u9487", "4110": "\u5a67", "4111": "\u6829", "4112": "\u7425", "4113": "\u57b8", "4114": "\u6fa7", "4115": "\u74f4", "4116": "\u66a7", "4117": "\u914c", "4118": "\u8113", "4119": "\u9e9d", "4120": "\u7bf7", "4121": "\u7b2e", "4122": "\u797a", "4123": "\u9a85", "4124": "\u6d04", "4125": "\u5d69", "4126": "\u7802", "4127": "\u8bc2", "4128": "\u9ab0", "4129": "\u8c14", "4130": "\u8c1f", "4131": "\u6c40", "4132": "\u8708", "4133": "\u86a3", "4134": "\u796f", "4135": "\u918b", "4136": "\u6e0d", "4137": "\u6a35", "4138": "\u5c90", "4139": "\u54b3", "4140": "\u53a5", "4141": "\u57dd", "4142": "\u8392", "4143": "\u6dbf", "4144": "\u5f6a", "4145": "\u76ce", "4146": "\u4e19", "4147": "\u7184", "4148": "\u5ed6", "4149": "\u4ed1", "4150": "\u54fd", "4151": "\u7a1e", "4152": "\u88a4", "4153": "\u8882", "4154": "\u6f2f", "4155": "\u6e32", "4156": "\u6d9e", "4157": "\u2478", "4158": "\u5996", "4159": "\u9885", "4160": "\u64d2", "4161": "\u5162", "4162": "\u849c", "4163": "\u6fee", "4164": "\u97a0", "4165": "\u6da3", "4166": "\u6f4d", "4167": "\u7f42", "4168": "\u86c0", "4169": "\u9606", "4170": "\u9672", "4171": "\u8bab", "4172": "\u9cab", "4173": "\u69cc", "4174": "\u6382", "4175": "\u5482", "4176": "\u8fe9", "4177": "\u64a9", "4178": "\u6930", "4179": "\u5a40", "4180": "\u8d6d", "4181": "\u4fe8", "4182": "\u55e1", "4183": "\u65d6", "4184": "\u65ce", "4185": "\u6cde", "4186": "\u60f6", "4187": "\u8237", "4188": "\u6e11", "4189": "\u6d2e", "4190": "\u8d49", "4191": "\u6963", "4192": "\u8c0f", "4193": "\u909d", "4194": "\u9157", "4195": "\u704f", "4196": "\u7f30", "4197": "\u5315", "4198": "\u5492", "4199": "\u873b", "4200": "\u8713", "4201": "\u7825", "4202": "\u6d07", "4203": "\u9e25", "4204": "\u8e7c", "4205": "\u8707", "4206": "\u9cde", "4207": "\u972d", "4208": "\u7b94", "4209": "\u889c", "4210": "\u6809", "4211": "\u525c", "4212": "\u7c3f", "4213": "\u7f0e", "4214": "\u7ebe", "4215": "\u4f2b", "4216": "\u78e1", "4217": "\u5955", "4218": "\u6ea7", "4219": "\u67e9", "4220": "\u916f", "4221": "\uff57", "4222": "\u9511", "4223": "\u7f81", "4224": "\u7fb9", "4225": "\u75fc", "4226": "\u837b", "4227": "\u576f", "4228": "\u2103", "4229": "\u6e0e", "4230": "\u7a79", "4231": "\u9890", "4232": "\u7eee", "4233": "\u6fb9", "4234": "\u6c85", "4235": "\u9149", "4236": "\u95fe", "4237": "\u5729", "4238": "\u96c9", "4239": "\u68e3", "4240": "\u67d2", "4241": "\u5ac9", "4242": "\u4f0e", "4243": "\u90b0", "4244": "\u5bee", "4245": "\u5a04", "4246": "\u9122", "4247": "\u7c95", "4248": "\u6308", "4249": "\u5a23", "4250": "\u655d", "4251": "\u94f0", "4252": "\u6ec7", "4253": "\u637b", "4254": "\u578c", "4255": "\u8a07", "4256": "\u6ba1", "4257": "\u5e5b", "4258": "\u96a7", "4259": "\u97f6", "4260": "\u77a5", "4261": "\u776c", "4262": "\u70e9", "4263": "\u62a0", "4264": "\u5471", "4265": "\u8783", "4266": "\u58f9", "4267": "\u5156", "4268": "\u7583", "4269": ".", "4270": "\u655b", "4271": "\u7f44", "4272": "\u58f6", "4273": "\u6059", "4274": "\u6123", "4275": "\u87e0", "4276": "\u5d82", "4277": "\u5c34", "4278": "\u5c2c", "4279": "\u90dd", "4280": "\u965b", "4281": "\u94f1", "4282": "\u595a", "4283": "\u7be1", "4284": "\u9990", "4285": "\u85e9", "4286": "\u684e", "4287": "\u688f", "4288": "\u6f2a", "4289": "\u8bcb", "4290": "\u6ed3", "4291": "\u59af", "4292": "\u5a0c", "4293": "\u8703", "4294": "\u7599", "4295": "\u7629", "4296": "\u4ee8", "4297": "\u542e", "4298": "\u8235", "4299": "\u7f94", "4300": "\u6482", "4301": "\u80fc", "4302": "\u80dd", "4303": "\u5591", "4304": "\u8473", "4305": "\u8564", "4306": "\u8c32", "4307": "\u6345", "4308": "\u73e9", "4309": "\u7ec2", "4310": "\u6390", "4311": "\u8682", "4312": "\u86b1", "4313": "\u75b8", "4314": "\u8e09", "4315": "\u8dc4", "4316": "\u612b", "4317": "\u9b47", "4318": "\u970e", "4319": "\u949d", "4320": "\u6d95", "4321": "\u6215", "4322": "\u5624", "4323": "\u76cf", "4324": "\u68c2", "4325": "\u6979", "4326": "\u4ec4", "4327": "\u5ba6", "4328": "\u71ee", "4329": "\u92ae", "4330": "\u530d", "4331": "\u5310", "4332": "\u5b75", "4333": "\u86e4", "4334": "\u6f66", "4335": "\u6874", "4336": "\u9955", "4337": "\u992e", "4338": "\u97ed", "4339": "\u9cdd", "4340": "\u8364", "4341": "\u5992", "4342": "\u8884", "4343": "\u5a76", "4344": "\u62fd", "4345": "\u7980", "4346": "\u6005", "4347": "\u6893", "4348": "\u80c4", "4349": "\u8e0c", "4350": "\u8e87", "4351": "\u4ec3", "4352": "\u9052", "4353": "\u81fc", "4354": "\u9ca2", "4355": "\u68b5", "4356": "\u7708", "4357": "\u6901", "4358": "\u9af9", "4359": "\u76bf", "4360": "\u968d", "4361": "\u752c", "4362": "\u742c", "4363": "\u9701", "4364": "\u6f36", "4365": "\u9a74", "4366": "\u8fe6", "4367": "\u5533", "4368": "\u7080", "4369": "\u5e19", "4370": "\u7409", "4371": "\u7b5a", "4372": "\u7c9d", "4373": "\u94ec", "4374": "\u80f0", "4375": "\u75bd", "4376": "\u5a77", "4377": "\u7235", "4378": "\u6619", "4379": "\u63ff", "4380": "\u996c", "4381": "\u9a77", "4382": "\u9a79", "4383": "\u96ef", "4384": "\u5522", "4385": "\u5431", "4386": "\u62c7", "4387": "\u747e", "4388": "\u5e4c", "4389": "\u9756", "4390": "\u8fab", "4391": "\u6dd9", "4392": "\u6d0c", "4393": "\u82de", "4394": "\u7cc5", "4395": "\u70c3", "4396": "\u8385", "4397": "\u729f", "4398": "\u6fc2", "4399": "\u8304", "4400": "\u5494", "4401": "\u9a9b", "4402": "\u74ef", "4403": "\u73f2", "4404": "\u8681", "4405": "\u8dfa", "4406": "\u6dec", "4407": "\u6ee6", "4408": "\u5892", "4409": "\u5a09", "4410": "\u607a", "4411": "\u83e9", "4412": "\u98da", "4413": "\u8431", "4414": "\u5a7a", "4415": "\u951f", "4416": "\u620a", "4417": "\u620c", "4418": "\u59ec", "4419": "\u4e10", "4420": "\u73ba", "4421": "\u782d", "4422": "\u535e", "4423": "\u568e", "4424": "\u5555", "4425": "\u6ec2", "4426": "\u6cb1", "4427": "\u8baa", "4428": "\u6942", "4429": "\u8446", "4430": "\u832f", "4431": "\u82d3", "4432": "\u5c8c", "4433": "\u6dc6", "4434": "\u7622", "4435": "\u2160", "4436": "\u8338", "4437": "\u8e41", "4438": "\u8df9", "4439": "\u781a", "4440": "\u667e", "4441": "\u7168", "4442": "\u55c5", "4443": "\u87d1", "4444": "\u7eab", "4445": "\u7efa", "4446": "\u564e", "4447": "\u94e3", "4448": "\u607d", "4449": "\u7430", "4450": "\u5eb6", "4451": "\u8782", "4452": "\u6f31", "4453": "\u631e", "4454": "\u55df", "4455": "\u64b7", "4456": "\u7391", "4457": "\u557b", "4458": "\u83ba", "4459": "\u6c8c", "4460": "\u8e47", "4461": "\u9984", "4462": "\u9968", "4463": "\u556d", "4464": "\u7fce", "4465": "\u6e98", "4466": "\u7751", "4467": "\u83a8", "4468": "\u83ea", "4469": "\u9534", "4470": "\u6775", "4471": "\u4eb5", "4472": "\u8210", "4473": "\u5457", "4474": "\u7b06", "4475": "\u549b", "4476": "\u4e2b", "4477": "\u75e3", "4478": "\u6be1", "4479": "\u956f", "4480": "\u630e", "4481": "\u5e27", "4482": "\u502c", "4483": "\u7f19", "4484": "\u584d", "4485": "\u6864", "4486": "\u72f0", "4487": "\u72de", "4488": "\u8314", "4489": "\u7bfc", "4490": "\u8db8", "4491": "\u8bb9", "4492": "\u6c5d", "4493": "\u8bd9", "4494": "\u9041", "4495": "\u6006", "4496": "\u7765", "4497": "\u7768", "4498": "\u4fa9", "4499": "\u70ec", "4500": "\u86d0", "4501": "\u87cb", "4502": "\u87c0", "4503": "\u62c4", "4504": "\u53fd", "4505": "\u55b3", "4506": "\u9631", "4507": "\u85ae", "4508": "\u557e", "4509": "\u6934", "4510": "\u6a97", "4511": "\u67e0", "4512": "\u6aac", "4513": "\u7239", "4514": "\u94ff", "4515": "\u9535", "4516": "\u5f95", "4517": "\u599e", "4518": "\u7aa6", "4519": "\u5261", "4520": "\u6f46", "4521": "\u86d8", "4522": "\u86ac", "4523": "\u502d", "4524": "\u86ce", "4525": "\u6bc2", "4526": "\u6cbd", "4527": "\u5ae3", "4528": "\u63ac", "4529": "\u6387", "4530": "\u8bb7", "4531": "-", "4532": "\u8bfd", "4533": "\u8c24", "4534": "\u9649", "4535": "\u5d27", "4536": "\u64b8", "4537": "\u82eb", "4538": "\u55f2", "4539": "\u683e", "4540": "\u7ef6", "4541": "\u5fcf", "4542": "\u5208", "4543": "\u8c36", "4544": "\u7fb8", "4545": "\u82d5", "4546": "\u609a", "4547": "\u5c50", "4548": "\u6248", "4549": "\u69db", "4550": "\u8715", "4551": "\u7f9f", "4552": "\u77eb", "4553": "\u88f1", "4554": "\u5f64", "4555": "\u9edf", "4556": "\u80ed", "4557": "\u812f", "4558": "\u6d93", "4559": "\u8983", "4560": "\u5889", "4561": "\u61cb", "4562": "\u5cab", "4563": "\u6f5e", "4564": "\u96cd", "4565": "\u8543", "4566": "\u9eb8", "4567": "\u9e2c", "4568": "\u9e5a", "4569": "\u542d", "4570": "\u8dbf", "4571": "\u8d45", "4572": "\u50a3", "4573": "\u5088", "4574": "\u50f3", "4575": "\u9095", "4576": "\u4eeb", "4577": "\u54ad", "4578": "\u6f8d", "4579": "\u5914", "4580": "\u6e4e", "4581": "\u891a", "4582": "\u64ce", "4583": "\u6421", "4584": "\u7f9a", "4585": "\u4edf", "4586": "\u78ec", "4587": "\u9a8a", "4588": "\u7a37", "4589": "\u7a51", "4590": "\u8c2a", "4591": "\u5739", "4592": "\u6c68", "4593": "\u917e", "4594": "\u8d3c", "4595": "\u8c12", "4596": "\u6b39", "4597": "\u78a3", "4598": "\u8037", "4599": "\u7110", "4600": "\u9556", "4601": "\u63cd", "4602": "\u565c", "4603": "\u4f84", "4604": "\u8e4b", "4605": "\u84ca", "4606": "\u8340", "4607": "\u6d5a", "4608": "\u9c87", "4609": "\u7b4f", "4610": "\u6d54", "4611": "\u86f8", "4612": "\u871e", "4613": "\u85d5", "4614": "\u8424", "4615": "\u7cbc", "4616": "\u9ee2", "4617": "\u626a", "4618": "\u7504", "4619": "\u556c", "4620": "\u84e5", "4621": "\u4fd0", "4622": "\u60bb", "4623": "\u8511", "4624": "\u4f5d", "4625": "\u507b", "4626": "\u78fa", "4627": "\u7960", "4628": "\u8bf0", "4629": "\u777f", "4630": "\u81fe", "4631": "\u6657", "4632": "\u7f2b", "4633": "\u724d", "4634": "\u7693", "4635": "\u840b", "4636": "\u71f9", "4637": "\u5b34", "4638": "\u559f", "4639": "\u75c2", "4640": "\u59be", "4641": "\u877c", "4642": "\u63d6", "4643": "\u8e05", "4644": "\u5ebe", "4645": "\u8e52", "4646": "\u8dda", "4647": "\u6ee2", "4648": "\u87fe", "4649": "\u94ee", "4650": "\u66dc", "4651": "\u8d58", "4652": "\u5a55", "4653": "\u7601", "4654": "\u7663", "4655": "\u76b2", "4656": "\u79ed", "4657": "+", "4658": "\uff1e", "4659": "\u7cdc", "4660": "\u5429", "4661": "\u5b6c", "4662": "\u539d", "4663": "\u8572", "4664": "\u90b3", "4665": "\u8bd8", "4666": "\uff3a", "4667": "\u6f62", "4668": "\u814b", "4669": "\u88d8", "4670": "\u7325", "4671": "\u8d67", "4672": "\u5e9a", "4673": "\u9a6f", "4674": "`", "4675": "\u9f88", "4676": "\u9f8b", "4677": "\u71a8", "4678": "\u7aa0", "4679": "\u58c5", "4680": "\u6635", "4681": "\u79a7", "4682": "\u5997", "4683": "?", "4684": "\u5eea", "4685": "\u6a58", "4686": "\u828b", "4687": "\u573b", "4688": "\u5773", "4689": "\u57ef", "4690": "\u8be4", "4691": "\u75de", "4692": "\u9161", "4693": "\u90eb", "4694": "\u9e69", "4695": "\u9cd7", "4696": "\u7350", "4697": "\u8816", "4698": "\u853a", "4699": "\u94d0", "4700": "\u6ecf", "4701": "\u9685", "4702": "\u564c", "4703": "\u64b5", "4704": "\u5b62", "4705": "\u7bd3", "4706": "\u85b9", "4707": "\u9604", "4708": "\u54c6", "4709": "\u55e6", "4710": "\u5eff", "4711": "\u90c5", "4712": "\u8fe5", "4713": "\u9004", "4714": "\u2030", "4715": "\u85d0", "4716": "\u2170", "4717": "\u2171", "4718": "\u7eb0", "4719": "\u6bfd", "4720": "\u5a13", "4721": "\u8638", "4722": "\u752d", "4723": "\u8004", "4724": "\u800b", "4725": "\u6ef9", "4726": "\u5556", "4727": "\u795a", "4728": "\u5ea5", "4729": "\u8559", "4730": "\u948d", "4731": "\u948b", "4732": "\u956d", "4733": "\u7f33", "4734": "\u9773", "4735": "\u5b93", "4736": "\u6e9f", "4737": "\u679e", "4738": "1", "4739": "\u86ca", "4740": "\u783c", "4741": "\u7bc1", "4742": "\u5599", "4743": "\u4edd", "4744": "\u9621", "4745": "\u6c8f", "4746": "\u60ed", "4747": "\u5ad4", "4748": "\u6840", "4749": "\u9f9b", "4750": "\u7747", "4751": "\u86a9", "4752": "\u77b5", "4753": "\u9e57", "4754": "\u6485", "4755": "\u8d94", "4756": "\u8d84", "4757": "\u781d", "4758": "\u6b8d", "4759": "\u5499", "4760": "\u621b", "4761": "\u765c", "4762": "\u7fd5", "4763": "\u8ba3", "4764": "\u55bd", "4765": "\u60c6", "4766": "\u6004", "4767": "\u975b", "4768": "\u63b3", "4769": "\u95f5", "4770": "\u778c", "4771": "\u6c4a", "4772": "\u8244", "4773": "\u6868", "4774": "\u5768", "4775": "\u65ab", "4776": "\u748b", "4777": "\u7baa", "4778": "\u7548", "4779": "\u76c2", "4780": "\u82cc", "4781": "\u8027", "4782": "\u62c8", "4783": "\u7ba2", "4784": "\u5541", "4785": "\u5658", "4786": "\u5edb", "4787": "\u6ce0", "4788": "\u7cb3", "4789": "\u82d2", "4790": "\u8934", "4791": "\u891b", "4792": "\u5c99", "4793": "\u8925", "4794": "\u7f04", "4795": "\u7afd", "4796": "\u7fe1", "4797": "\u783e", "4798": "\u83cf", "4799": "\u6a2f", "4800": "\u6845", "4801": "\u7579", "4802": "\u950f", "4803": "\u562d", "4804": "\u8537", "4805": "\u6c35", "4806": "\u67d8", "4807": "\u6886", "4808": "\u8f82", "4809": "\u5e44", "4810": "\u97eb", "4811": "\u6ceb", "4812": "\u7bd1", "4813": "\u6631", "4814": "\u665f", "4815": "\u86f3", "4816": "\u5f08", "4817": "\u7284", "4818": "\u52f0", "4819": "\u65ee", "4820": "\u65ef", "4821": "\u621f", "4822": "\u7f25", "4823": "\u7f08", "4824": "\u7f17", "4825": "\u80f4", "4826": "\u6d31", "4827": "\u62d7", "4828": "\u5f57", "4829": "\u4e15", "4830": "\u8469", "4831": "\u95f0", "4832": "\u7fbf", "4833": "\u62a1", "4834": "\u572a", "4835": "\u59f9", "4836": "\u51bd", "4837": "\u9aa5", "4838": "\u86fe", "4839": "\u76c5", "4840": "\u6d35", "4841": "\u82ce", "4842": "\u7893", "4843": "\u9b1f", "4844": "\u6860", "4845": "\u8d5d", "4846": "\u677c", "4847": "\u73de", "4848": "\u7ccc", "4849": "\u7c91", "4850": "\uff51", "4851": "\uff06", "4852": "\u95e9", "4853": "\u59aa", "4854": "\u9502", "4855": "\u9517", "4856": "\u998f", "4857": "\u5db7", "4858": "\u7317", "4859": "\u949b", "4860": "\u69ab", "4861": "\u89d1", "4862": "\u989a", "4863": "\u6b84", "4864": "\u5506", "4865": "\u54af", "4866": "\u549a", "4867": "\u54a3", "4868": "\u8c29", "4869": "\u5243", "4870": "\u84d1", "4871": "\u52d0", "4872": "\u4f64", "4873": "\u652b", "4874": "\u5f40", "4875": "\u80bd", "4876": "\u919b", "4877": "\u7b24", "4878": "\u78b4", "4879": "\u4ffe", "4880": "\u6d8e", "4881": "\u53fb", "4882": "\u2192", "4883": "\u5e96", "4884": "\u8026", "4885": "\u80ea", "4886": "\u72e9", "4887": "\u6e5f", "4888": "\u73ae", "4889": "\u9068", "4890": "\u6aa9", "4891": "\u94c6", "4892": "\u59ab", "4893": "\u57d9", "4894": "\u535f", "4895": "\u5549", "4896": "\u75b4", "4897": "\u6e1a", "4898": "\u8368", "4899": "\u5cb7", "4900": "\u7bdd", "4901": "\u99a5", "4902": "\u9cad", "4903": "\u90a1", "4904": "\u9706", "4905": "\u9b23", "4906": "\u7172", "4907": "\u715c", "4908": "\u4f09", "4909": "\u4fea", "4910": "\u94d9", "4911": "\u75f1", "4912": "\u6600", "4913": "\u6c94", "4914": "\u749c", "4915": "\u5e61", "4916": "\u8bce", "4917": "\u4e1e", "4918": "\u8198", "4919": "\u97ea", "4920": "\u9708", "4921": "\u5345", "4922": "\u807f", "4923": "\u5800", "4924": "\u9e73", "4925": "\u5501", "4926": "\u9537", "4927": "\u768b", "4928": "\u712f", "4929": "|", "4930": "O", "4931": "\u740f", "4932": "\u4fce", "4933": "\u9e8b", "4934": "\u6002", "4935": "\u8148", "4936": "\u836a", "4937": "\u8c15", "4938": "\u68f0", "4939": "\t", "4940": "\u8e2e", "4941": "\u634b", "4942": "\u55ef", "4943": "\u9ab7", "4944": "\u9ac5", "4945": "\u9a9f", "4946": "\u90cf", "4947": "\u7889", "4948": "\u7aa8", "4949": "\u9e66", "4950": "\u9e49", "4951": "\u9cdf", "4952": "\u9c91", "4953": "\u8334", "4954": "\u6d91", "4955": "\u51fc", "4956": "\u95f3", "4957": "\u6862", "4958": "\u802a", "4959": "\u84d3", "4960": "\u6989", "4961": "\u8bc5", "4962": "\u7166", "4963": "\u6175", "4964": "\u82be", "4965": "\u72e1", "4966": "\u72ef", "4967": "\u82ab", "4968": "\u8d30", "4969": "\u664c", "4970": "\u6078", "4971": "\u6b46", "4972": "\u623e", "4973": "\u89da", "4974": "\u8200", "4975": "\u6641", "4976": "\u9ee0", "4977": "\u7b08", "4978": "\u82dc", "4979": "\u84ff", "4980": "\u8815", "4981": "\u86df", "4982": "\u62bb", "4983": "\u8182", "4984": "\u91ba", "4985": "\u8a8a", "4986": "\u586c", "4987": "\u5942", "4988": "\u5412", "4989": "\u62bf", "4990": "\u5366", "4991": "\u90ac", "4992": "\u918d", "4993": "\u9190", "4994": "\u8bdf", "4995": "\u4fda", "4996": "\u67b7", "4997": "\u69ce", "4998": "\u8052", "4999": "\u9f83", "5000": "\u9f89", "5001": "\u8869", "5002": "\u8171", "5003": "\u7252", "5004": "\u93d6", "5005": "\u88c6", "5006": "\u523d", "5007": "\u90d3", "5008": "\u6194", "5009": "\u60b4", "5010": "\u61d1", "5011": "\u6b43", "5012": "\u9563", "5013": "\u6de6", "5014": "\u03b1", "5015": "\u94a1", "5016": "\u733e", "5017": "\u55d6", "5018": "\u59e5", "5019": "\u91dc", "5020": "\u9495", "5021": "\u787c", "5022": "\u94bd", "5023": "\u94cc", "5024": "\u75b9", "5025": "0", "5026": "\u948e", "5027": "\u5f11", "5028": "\u6cf7", "5029": "\u63f6", "5030": "\u63c4", "5031": "\u8f7a", "5032": "\u8f8e", "5033": "\u8f9a", "5034": "\u714a", "5035": "\u7fb2", "5036": "\u9e92", "5037": "\u5a06", "5038": "\u8f87", "5039": "\u69f2", "5040": "\u732c", "5041": "\u75e2", "5042": "\u6371", "5043": "\u75b1", "5044": "P", "5045": "\u723b", "5046": "\u5477", "5047": "\u8309", "5048": "\u9aeb", "5049": "\u5eb5", "5050": "\u4f3d", "5051": "\u81c0", "5052": "L", "5053": "\u77f8", "5054": "\u8d53", "5055": "\u695d", "5056": "\u5981", "5057": "\u6c74", "5058": "\u60fa", "5059": "\u91b4", "5060": "\u8c62", "5061": "\uff1d", "5062": "\u8c89", "5063": "\u915e", "5064": "\u58ec", "5065": "\u69ff", "5066": "\u59d7", "5067": "\u748e", "5068": "v", "5069": "\u8be9", "5070": "\u98d5", "5071": "\u6f4b", "5072": "\u6edf", "5073": "\u94e0", "5074": "\u5cbf", "5075": "\u82d8", "5076": "\u9785", "5077": "\u9cc4", "5078": "\u73d9", "5079": "\u2163", "5080": "\u2164", "5081": "\u7f5f", "5082": "\u9c85", "5083": "\u741a", "5084": "d", "5085": "a", "5086": "t", "5087": "]", "5088": "i", "5089": "n", "5090": "\u6221", "5091": "\u727e", "5092": "\u4f43", "5093": "g", "5094": "\u94ac", "5095": "\u8c11", "5096": "\u563b", "5097": "\u9a9d", "5098": "\u7827", "5099": "\u989e", "5100": "\u4e93", "5101": "\u822b", "5102": "\u5b51", "5103": "\u7116", "5104": "\u8069", "5105": "\u6b93", "5106": "\u9b3b", "5107": "\u6ca3", "5108": "\u7b75", "5109": "\u826e", "5110": "\u9b03", "5111": "\u8e49", "5112": "\u8dce", "5113": "\u3228", "5114": "\u67b0", "5115": "\u63ae", "5116": "\u933e", "5117": "\u7f8c", "5118": "\u87b3", "5119": "\u9697", "5120": "\u9e44", "5121": "\u524c", "5122": "\u93ca", "5123": "\u5df3", "5124": "\u9e5e", "5125": "\u5241", "5126": "\u8c17", "5127": "\u607f", "5128": "\u8bee", "5129": "\u8118", "5130": "\u8160", "5131": "\u830c", "5132": "\u917d", "5133": "\u7094", "5134": "\u8c21", "5135": "\u2225", "5136": "\u75b5", "5137": "\u5453", "5138": "\u5ba5", "5139": "\u94a4", "5140": "\u9997", "5141": "\u89cf", "5142": "\u6a65", "5143": "\u4f70", "5144": "\u9e22", "5145": "\u64e2", "5146": "\u6cf1", "5147": "\u75c8", "5148": "\u835c", "5149": "\u6654", "5150": "\u3014", "5151": "\u3015", "5152": "\u772d", "5153": "\u81ca", "5154": "\u7619", "5155": "\u5d02", "5156": "\u65cc", "5157": "\u4f5a", "5158": "\u8bd2", "5159": "\u6426", "5160": "\u5ffb", "5161": "\u723f", "5162": "\u72f8", "5163": "\u86a7", "5164": "\u8169", "5165": "\u9179", "5166": "\u9ecf", "5167": "\u51c7", "5168": "\u8e39"}